Compiled from "MultilineTextField.java"
public class net.minecraft.client.gui.components.MultilineTextField {
  private static final org.slf4j.Logger LOGGER;

  public static final int NO_LIMIT;

  private static final int LINE_SEEK_PIXEL_BIAS;

  private final net.minecraft.client.gui.Font font;

  private final java.util.List<net.minecraft.client.gui.components.MultilineTextField$StringView> displayLines;

  private java.lang.String value;

  private int cursor;

  private int selectCursor;

  private boolean selecting;

  private int characterLimit;

  private int lineLimit;

  private final int width;

  private java.util.function.Consumer<java.lang.String> valueListener;

  private java.lang.Runnable cursorListener;

  public net.minecraft.client.gui.components.MultilineTextField(net.minecraft.client.gui.Font, int);
    Code:
         0: aload_0
         1: invokespecial #52                 // Method java/lang/Object."<init>":()V
         4: aload_0
         5: invokestatic  #58                 // Method com/google/common/collect/Lists.newArrayList:()Ljava/util/ArrayList;
         8: putfield      #60                 // Field displayLines:Ljava/util/List;
        11: aload_0
        12: ldc           #25                 // int 2147483647
        14: putfield      #62                 // Field characterLimit:I
        17: aload_0
        18: ldc           #25                 // int 2147483647
        20: putfield      #64                 // Field lineLimit:I
        23: aload_0
        24: invokedynamic #83,  0             // InvokeDynamic #0:accept:()Ljava/util/function/Consumer;
        29: putfield      #85                 // Field valueListener:Ljava/util/function/Consumer;
        32: aload_0
        33: invokedynamic #94,  0             // InvokeDynamic #1:run:()Ljava/lang/Runnable;
        38: putfield      #96                 // Field cursorListener:Ljava/lang/Runnable;
        41: aload_0
        42: aload_1
        43: putfield      #98                 // Field font:Lnet/minecraft/client/gui/Font;
        46: aload_0
        47: iload_2
        48: putfield      #100                // Field width:I
        51: aload_0
        52: ldc           #102                // String
        54: invokevirtual #105                // Method setValue:(Ljava/lang/String;)V
        57: return

  public int characterLimit();
    Code:
         0: aload_0
         1: getfield      #62                 // Field characterLimit:I
         4: ireturn

  public void setCharacterLimit(int);
    Code:
         0: iload_1
         1: ifge          14
         4: new           #112                // class java/lang/IllegalArgumentException
         7: dup
         8: ldc           #114                // String Character limit cannot be negative
        10: invokespecial #116                // Method java/lang/IllegalArgumentException."<init>":(Ljava/lang/String;)V
        13: athrow
        14: aload_0
        15: iload_1
        16: putfield      #62                 // Field characterLimit:I
        19: return

  public void setLineLimit(int);
    Code:
         0: iload_1
         1: ifge          14
         4: new           #112                // class java/lang/IllegalArgumentException
         7: dup
         8: ldc           #114                // String Character limit cannot be negative
        10: invokespecial #116                // Method java/lang/IllegalArgumentException."<init>":(Ljava/lang/String;)V
        13: athrow
        14: aload_0
        15: iload_1
        16: putfield      #64                 // Field lineLimit:I
        19: return

  public boolean hasCharacterLimit();
    Code:
         0: aload_0
         1: getfield      #62                 // Field characterLimit:I
         4: ldc           #25                 // int 2147483647
         6: if_icmpeq     13
         9: iconst_1
        10: goto          14
        13: iconst_0
        14: ireturn

  public boolean hasLineLimit();
    Code:
         0: aload_0
         1: getfield      #64                 // Field lineLimit:I
         4: ldc           #25                 // int 2147483647
         6: if_icmpeq     13
         9: iconst_1
        10: goto          14
        13: iconst_0
        14: ireturn

  public void setValueListener(java.util.function.Consumer<java.lang.String>);
    Code:
         0: aload_0
         1: aload_1
         2: putfield      #85                 // Field valueListener:Ljava/util/function/Consumer;
         5: return

  public void setCursorListener(java.lang.Runnable);
    Code:
         0: aload_0
         1: aload_1
         2: putfield      #96                 // Field cursorListener:Ljava/lang/Runnable;
         5: return

  public void setValue(java.lang.String);
    Code:
         0: aload_0
         1: aload_1
         2: iconst_0
         3: invokevirtual #131                // Method setValue:(Ljava/lang/String;Z)V
         6: return

  public void setValue(java.lang.String, boolean);
    Code:
         0: aload_0
         1: aload_1
         2: invokevirtual #136                // Method truncateFullText:(Ljava/lang/String;)Ljava/lang/String;
         5: astore_3
         6: iload_2
         7: ifne          19
        10: aload_0
        11: aload_3
        12: invokevirtual #140                // Method overflowsLineLimit:(Ljava/lang/String;)Z
        15: ifeq          19
        18: return
        19: aload_0
        20: aload_3
        21: putfield      #144                // Field value:Ljava/lang/String;
        24: aload_0
        25: aload_0
        26: getfield      #144                // Field value:Ljava/lang/String;
        29: invokevirtual #147                // Method java/lang/String.length:()I
        32: putfield      #149                // Field cursor:I
        35: aload_0
        36: aload_0
        37: getfield      #149                // Field cursor:I
        40: putfield      #151                // Field selectCursor:I
        43: aload_0
        44: invokevirtual #154                // Method onValueChange:()V
        47: return

  public java.lang.String value();
    Code:
         0: aload_0
         1: getfield      #144                // Field value:Ljava/lang/String;
         4: areturn

  public void insertText(java.lang.String);
    Code:
         0: aload_1
         1: invokevirtual #160                // Method java/lang/String.isEmpty:()Z
         4: ifeq          15
         7: aload_0
         8: invokevirtual #163                // Method hasSelection:()Z
        11: ifne          15
        14: return
        15: aload_0
        16: aload_1
        17: iconst_1
        18: invokestatic  #169                // Method net/minecraft/util/StringUtil.filterText:(Ljava/lang/String;Z)Ljava/lang/String;
        21: invokevirtual #172                // Method truncateInsertionText:(Ljava/lang/String;)Ljava/lang/String;
        24: astore_2
        25: aload_0
        26: invokevirtual #176                // Method getSelected:()Lnet/minecraft/client/gui/components/MultilineTextField$StringView;
        29: astore_3
        30: new           #178                // class java/lang/StringBuilder
        33: dup
        34: aload_0
        35: getfield      #144                // Field value:Ljava/lang/String;
        38: invokespecial #179                // Method java/lang/StringBuilder."<init>":(Ljava/lang/String;)V
        41: aload_3
        42: getfield      #182                // Field net/minecraft/client/gui/components/MultilineTextField$StringView.beginIndex:I
        45: aload_3
        46: getfield      #185                // Field net/minecraft/client/gui/components/MultilineTextField$StringView.endIndex:I
        49: aload_2
        50: invokevirtual #189                // Method java/lang/StringBuilder.replace:(IILjava/lang/String;)Ljava/lang/StringBuilder;
        53: invokevirtual #192                // Method java/lang/StringBuilder.toString:()Ljava/lang/String;
        56: astore        4
        58: aload_0
        59: aload         4
        61: invokevirtual #140                // Method overflowsLineLimit:(Ljava/lang/String;)Z
        64: ifeq          68
        67: return
        68: aload_0
        69: aload         4
        71: putfield      #144                // Field value:Ljava/lang/String;
        74: aload_0
        75: aload_3
        76: getfield      #182                // Field net/minecraft/client/gui/components/MultilineTextField$StringView.beginIndex:I
        79: aload_2
        80: invokevirtual #147                // Method java/lang/String.length:()I
        83: iadd
        84: putfield      #149                // Field cursor:I
        87: aload_0
        88: aload_0
        89: getfield      #149                // Field cursor:I
        92: putfield      #151                // Field selectCursor:I
        95: aload_0
        96: invokevirtual #154                // Method onValueChange:()V
        99: return

  public void deleteText(int);
    Code:
         0: aload_0
         1: invokevirtual #163                // Method hasSelection:()Z
         4: ifne          28
         7: aload_0
         8: aload_0
         9: getfield      #149                // Field cursor:I
        12: iload_1
        13: iadd
        14: iconst_0
        15: aload_0
        16: getfield      #144                // Field value:Ljava/lang/String;
        19: invokevirtual #147                // Method java/lang/String.length:()I
        22: invokestatic  #202                // Method net/minecraft/util/Mth.clamp:(III)I
        25: putfield      #151                // Field selectCursor:I
        28: aload_0
        29: ldc           #102                // String
        31: invokevirtual #204                // Method insertText:(Ljava/lang/String;)V
        34: return

  public int cursor();
    Code:
         0: aload_0
         1: getfield      #149                // Field cursor:I
         4: ireturn

  public void setSelecting(boolean);
    Code:
         0: aload_0
         1: iload_1
         2: putfield      #208                // Field selecting:Z
         5: return

  public net.minecraft.client.gui.components.MultilineTextField$StringView getSelected();
    Code:
         0: new           #9                  // class net/minecraft/client/gui/components/MultilineTextField$StringView
         3: dup
         4: aload_0
         5: getfield      #151                // Field selectCursor:I
         8: aload_0
         9: getfield      #149                // Field cursor:I
        12: invokestatic  #214                // Method java/lang/Math.min:(II)I
        15: aload_0
        16: getfield      #151                // Field selectCursor:I
        19: aload_0
        20: getfield      #149                // Field cursor:I
        23: invokestatic  #217                // Method java/lang/Math.max:(II)I
        26: invokespecial #220                // Method net/minecraft/client/gui/components/MultilineTextField$StringView."<init>":(II)V
        29: areturn

  public int getLineCount();
    Code:
         0: aload_0
         1: getfield      #60                 // Field displayLines:Ljava/util/List;
         4: invokeinterface #226,  1          // InterfaceMethod java/util/List.size:()I
         9: ireturn

  public int getLineAtCursor();
    Code:
         0: iconst_0
         1: istore_1
         2: iload_1
         3: aload_0
         4: getfield      #60                 // Field displayLines:Ljava/util/List;
         7: invokeinterface #226,  1          // InterfaceMethod java/util/List.size:()I
        12: if_icmpge     59
        15: aload_0
        16: getfield      #60                 // Field displayLines:Ljava/util/List;
        19: iload_1
        20: invokeinterface #231,  2          // InterfaceMethod java/util/List.get:(I)Ljava/lang/Object;
        25: checkcast     #9                  // class net/minecraft/client/gui/components/MultilineTextField$StringView
        28: astore_2
        29: aload_0
        30: getfield      #149                // Field cursor:I
        33: aload_2
        34: getfield      #182                // Field net/minecraft/client/gui/components/MultilineTextField$StringView.beginIndex:I
        37: if_icmplt     53
        40: aload_0
        41: getfield      #149                // Field cursor:I
        44: aload_2
        45: getfield      #185                // Field net/minecraft/client/gui/components/MultilineTextField$StringView.endIndex:I
        48: if_icmpgt     53
        51: iload_1
        52: ireturn
        53: iinc          1, 1
        56: goto          2
        59: iconst_m1
        60: ireturn

  public net.minecraft.client.gui.components.MultilineTextField$StringView getLineView(int);
    Code:
         0: aload_0
         1: getfield      #60                 // Field displayLines:Ljava/util/List;
         4: iload_1
         5: iconst_0
         6: aload_0
         7: getfield      #60                 // Field displayLines:Ljava/util/List;
        10: invokeinterface #226,  1          // InterfaceMethod java/util/List.size:()I
        15: iconst_1
        16: isub
        17: invokestatic  #202                // Method net/minecraft/util/Mth.clamp:(III)I
        20: invokeinterface #231,  2          // InterfaceMethod java/util/List.get:(I)Ljava/lang/Object;
        25: checkcast     #9                  // class net/minecraft/client/gui/components/MultilineTextField$StringView
        28: areturn

  public void seekCursor(net.minecraft.client.gui.components.Whence, int);
    Code:
         0: getstatic     #240                // Field net/minecraft/client/gui/components/MultilineTextField$1.$SwitchMap$net$minecraft$client$gui$components$Whence:[I
         3: aload_1
         4: invokevirtual #245                // Method net/minecraft/client/gui/components/Whence.ordinal:()I
         7: iaload
         8: tableswitch   { // 1 to 3

                       1: 36

                       2: 44

                       3: 57
                 default: 70
            }
        36: aload_0
        37: iload_2
        38: putfield      #149                // Field cursor:I
        41: goto          70
        44: aload_0
        45: dup
        46: getfield      #149                // Field cursor:I
        49: iload_2
        50: iadd
        51: putfield      #149                // Field cursor:I
        54: goto          70
        57: aload_0
        58: aload_0
        59: getfield      #144                // Field value:Ljava/lang/String;
        62: invokevirtual #147                // Method java/lang/String.length:()I
        65: iload_2
        66: iadd
        67: putfield      #149                // Field cursor:I
        70: aload_0
        71: aload_0
        72: getfield      #149                // Field cursor:I
        75: iconst_0
        76: aload_0
        77: getfield      #144                // Field value:Ljava/lang/String;
        80: invokevirtual #147                // Method java/lang/String.length:()I
        83: invokestatic  #202                // Method net/minecraft/util/Mth.clamp:(III)I
        86: putfield      #149                // Field cursor:I
        89: aload_0
        90: getfield      #96                 // Field cursorListener:Ljava/lang/Runnable;
        93: invokeinterface #249,  1          // InterfaceMethod java/lang/Runnable.run:()V
        98: aload_0
        99: getfield      #208                // Field selecting:Z
       102: ifne          113
       105: aload_0
       106: aload_0
       107: getfield      #149                // Field cursor:I
       110: putfield      #151                // Field selectCursor:I
       113: return

  public void seekCursorLine(int);
    Code:
         0: iload_1
         1: ifne          5
         4: return
         5: aload_0
         6: getfield      #98                 // Field font:Lnet/minecraft/client/gui/Font;
         9: aload_0
        10: getfield      #144                // Field value:Ljava/lang/String;
        13: aload_0
        14: invokevirtual #254                // Method getCursorLineView:()Lnet/minecraft/client/gui/components/MultilineTextField$StringView;
        17: getfield      #182                // Field net/minecraft/client/gui/components/MultilineTextField$StringView.beginIndex:I
        20: aload_0
        21: getfield      #149                // Field cursor:I
        24: invokevirtual #258                // Method java/lang/String.substring:(II)Ljava/lang/String;
        27: invokevirtual #263                // Method net/minecraft/client/gui/Font.width:(Ljava/lang/String;)I
        30: iconst_2
        31: iadd
        32: istore_2
        33: aload_0
        34: iload_1
        35: invokevirtual #265                // Method getCursorLineView:(I)Lnet/minecraft/client/gui/components/MultilineTextField$StringView;
        38: astore_3
        39: aload_0
        40: getfield      #98                 // Field font:Lnet/minecraft/client/gui/Font;
        43: aload_0
        44: getfield      #144                // Field value:Ljava/lang/String;
        47: aload_3
        48: getfield      #182                // Field net/minecraft/client/gui/components/MultilineTextField$StringView.beginIndex:I
        51: aload_3
        52: getfield      #185                // Field net/minecraft/client/gui/components/MultilineTextField$StringView.endIndex:I
        55: invokevirtual #258                // Method java/lang/String.substring:(II)Ljava/lang/String;
        58: iload_2
        59: invokevirtual #269                // Method net/minecraft/client/gui/Font.plainSubstrByWidth:(Ljava/lang/String;I)Ljava/lang/String;
        62: invokevirtual #147                // Method java/lang/String.length:()I
        65: istore        4
        67: aload_0
        68: getstatic     #272                // Field net/minecraft/client/gui/components/Whence.ABSOLUTE:Lnet/minecraft/client/gui/components/Whence;
        71: aload_3
        72: getfield      #182                // Field net/minecraft/client/gui/components/MultilineTextField$StringView.beginIndex:I
        75: iload         4
        77: iadd
        78: invokevirtual #274                // Method seekCursor:(Lnet/minecraft/client/gui/components/Whence;I)V
        81: return

  public void seekCursorToPoint(double, double);
    Code:
         0: dload_1
         1: invokestatic  #284                // Method net/minecraft/util/Mth.floor:(D)I
         4: istore        5
         6: dload_3
         7: aload_0
         8: getfield      #98                 // Field font:Lnet/minecraft/client/gui/Font;
        11: invokestatic  #290                // Method java/util/Objects.requireNonNull:(Ljava/lang/Object;)Ljava/lang/Object;
        14: pop
        15: ldc2_w        #291                // double 9.0d
        18: ddiv
        19: invokestatic  #284                // Method net/minecraft/util/Mth.floor:(D)I
        22: istore        6
        24: aload_0
        25: getfield      #60                 // Field displayLines:Ljava/util/List;
        28: iload         6
        30: iconst_0
        31: aload_0
        32: getfield      #60                 // Field displayLines:Ljava/util/List;
        35: invokeinterface #226,  1          // InterfaceMethod java/util/List.size:()I
        40: iconst_1
        41: isub
        42: invokestatic  #202                // Method net/minecraft/util/Mth.clamp:(III)I
        45: invokeinterface #231,  2          // InterfaceMethod java/util/List.get:(I)Ljava/lang/Object;
        50: checkcast     #9                  // class net/minecraft/client/gui/components/MultilineTextField$StringView
        53: astore        7
        55: aload_0
        56: getfield      #98                 // Field font:Lnet/minecraft/client/gui/Font;
        59: aload_0
        60: getfield      #144                // Field value:Ljava/lang/String;
        63: aload         7
        65: getfield      #182                // Field net/minecraft/client/gui/components/MultilineTextField$StringView.beginIndex:I
        68: aload         7
        70: getfield      #185                // Field net/minecraft/client/gui/components/MultilineTextField$StringView.endIndex:I
        73: invokevirtual #258                // Method java/lang/String.substring:(II)Ljava/lang/String;
        76: iload         5
        78: invokevirtual #269                // Method net/minecraft/client/gui/Font.plainSubstrByWidth:(Ljava/lang/String;I)Ljava/lang/String;
        81: invokevirtual #147                // Method java/lang/String.length:()I
        84: istore        8
        86: aload_0
        87: getstatic     #272                // Field net/minecraft/client/gui/components/Whence.ABSOLUTE:Lnet/minecraft/client/gui/components/Whence;
        90: aload         7
        92: getfield      #182                // Field net/minecraft/client/gui/components/MultilineTextField$StringView.beginIndex:I
        95: iload         8
        97: iadd
        98: invokevirtual #274                // Method seekCursor:(Lnet/minecraft/client/gui/components/Whence;I)V
       101: return

  public void selectWordAtCursor();
    Code:
         0: aload_0
         1: invokevirtual #297                // Method getPreviousWord:()Lnet/minecraft/client/gui/components/MultilineTextField$StringView;
         4: astore_1
         5: aload_0
         6: getstatic     #272                // Field net/minecraft/client/gui/components/Whence.ABSOLUTE:Lnet/minecraft/client/gui/components/Whence;
         9: aload_1
        10: getfield      #182                // Field net/minecraft/client/gui/components/MultilineTextField$StringView.beginIndex:I
        13: invokevirtual #274                // Method seekCursor:(Lnet/minecraft/client/gui/components/Whence;I)V
        16: aload_0
        17: iconst_1
        18: invokevirtual #299                // Method setSelecting:(Z)V
        21: aload_0
        22: getstatic     #272                // Field net/minecraft/client/gui/components/Whence.ABSOLUTE:Lnet/minecraft/client/gui/components/Whence;
        25: aload_1
        26: getfield      #185                // Field net/minecraft/client/gui/components/MultilineTextField$StringView.endIndex:I
        29: invokevirtual #274                // Method seekCursor:(Lnet/minecraft/client/gui/components/Whence;I)V
        32: return

  public boolean keyPressed(net.minecraft.client.input.KeyEvent);
    Code:
         0: aload_0
         1: aload_1
         2: invokevirtual #307                // Method net/minecraft/client/input/KeyEvent.hasShiftDown:()Z
         5: putfield      #208                // Field selecting:Z
         8: aload_1
         9: invokevirtual #310                // Method net/minecraft/client/input/KeyEvent.isSelectAll:()Z
        12: ifeq          33
        15: aload_0
        16: aload_0
        17: getfield      #144                // Field value:Ljava/lang/String;
        20: invokevirtual #147                // Method java/lang/String.length:()I
        23: putfield      #149                // Field cursor:I
        26: aload_0
        27: iconst_0
        28: putfield      #151                // Field selectCursor:I
        31: iconst_1
        32: ireturn
        33: aload_1
        34: invokevirtual #313                // Method net/minecraft/client/input/KeyEvent.isCopy:()Z
        37: ifeq          55
        40: invokestatic  #319                // Method net/minecraft/client/Minecraft.getInstance:()Lnet/minecraft/client/Minecraft;
        43: getfield      #323                // Field net/minecraft/client/Minecraft.keyboardHandler:Lnet/minecraft/client/KeyboardHandler;
        46: aload_0
        47: invokevirtual #326                // Method getSelectedText:()Ljava/lang/String;
        50: invokevirtual #331                // Method net/minecraft/client/KeyboardHandler.setClipboard:(Ljava/lang/String;)V
        53: iconst_1
        54: ireturn
        55: aload_1
        56: invokevirtual #334                // Method net/minecraft/client/input/KeyEvent.isPaste:()Z
        59: ifeq          77
        62: aload_0
        63: invokestatic  #319                // Method net/minecraft/client/Minecraft.getInstance:()Lnet/minecraft/client/Minecraft;
        66: getfield      #323                // Field net/minecraft/client/Minecraft.keyboardHandler:Lnet/minecraft/client/KeyboardHandler;
        69: invokevirtual #337                // Method net/minecraft/client/KeyboardHandler.getClipboard:()Ljava/lang/String;
        72: invokevirtual #204                // Method insertText:(Ljava/lang/String;)V
        75: iconst_1
        76: ireturn
        77: aload_1
        78: invokevirtual #340                // Method net/minecraft/client/input/KeyEvent.isCut:()Z
        81: ifeq          105
        84: invokestatic  #319                // Method net/minecraft/client/Minecraft.getInstance:()Lnet/minecraft/client/Minecraft;
        87: getfield      #323                // Field net/minecraft/client/Minecraft.keyboardHandler:Lnet/minecraft/client/KeyboardHandler;
        90: aload_0
        91: invokevirtual #326                // Method getSelectedText:()Ljava/lang/String;
        94: invokevirtual #331                // Method net/minecraft/client/KeyboardHandler.setClipboard:(Ljava/lang/String;)V
        97: aload_0
        98: ldc           #102                // String
       100: invokevirtual #204                // Method insertText:(Ljava/lang/String;)V
       103: iconst_1
       104: ireturn
       105: aload_1
       106: invokevirtual #343                // Method net/minecraft/client/input/KeyEvent.key:()I
       109: lookupswitch  { // 12

                     257: 474

                     259: 404

                     261: 439

                     262: 252

                     263: 216

                     264: 302

                     265: 288

                     266: 316

                     267: 326

                     268: 336

                     269: 370

                     335: 474
                 default: 483
            }
       216: aload_1
       217: invokevirtual #346                // Method net/minecraft/client/input/KeyEvent.hasControlDown:()Z
       220: ifeq          242
       223: aload_0
       224: invokevirtual #297                // Method getPreviousWord:()Lnet/minecraft/client/gui/components/MultilineTextField$StringView;
       227: astore_2
       228: aload_0
       229: getstatic     #272                // Field net/minecraft/client/gui/components/Whence.ABSOLUTE:Lnet/minecraft/client/gui/components/Whence;
       232: aload_2
       233: getfield      #182                // Field net/minecraft/client/gui/components/MultilineTextField$StringView.beginIndex:I
       236: invokevirtual #274                // Method seekCursor:(Lnet/minecraft/client/gui/components/Whence;I)V
       239: goto          250
       242: aload_0
       243: getstatic     #349                // Field net/minecraft/client/gui/components/Whence.RELATIVE:Lnet/minecraft/client/gui/components/Whence;
       246: iconst_m1
       247: invokevirtual #274                // Method seekCursor:(Lnet/minecraft/client/gui/components/Whence;I)V
       250: iconst_1
       251: ireturn
       252: aload_1
       253: invokevirtual #346                // Method net/minecraft/client/input/KeyEvent.hasControlDown:()Z
       256: ifeq          278
       259: aload_0
       260: invokevirtual #352                // Method getNextWord:()Lnet/minecraft/client/gui/components/MultilineTextField$StringView;
       263: astore_2
       264: aload_0
       265: getstatic     #272                // Field net/minecraft/client/gui/components/Whence.ABSOLUTE:Lnet/minecraft/client/gui/components/Whence;
       268: aload_2
       269: getfield      #182                // Field net/minecraft/client/gui/components/MultilineTextField$StringView.beginIndex:I
       272: invokevirtual #274                // Method seekCursor:(Lnet/minecraft/client/gui/components/Whence;I)V
       275: goto          286
       278: aload_0
       279: getstatic     #349                // Field net/minecraft/client/gui/components/Whence.RELATIVE:Lnet/minecraft/client/gui/components/Whence;
       282: iconst_1
       283: invokevirtual #274                // Method seekCursor:(Lnet/minecraft/client/gui/components/Whence;I)V
       286: iconst_1
       287: ireturn
       288: aload_1
       289: invokevirtual #346                // Method net/minecraft/client/input/KeyEvent.hasControlDown:()Z
       292: ifne          300
       295: aload_0
       296: iconst_m1
       297: invokevirtual #354                // Method seekCursorLine:(I)V
       300: iconst_1
       301: ireturn
       302: aload_1
       303: invokevirtual #346                // Method net/minecraft/client/input/KeyEvent.hasControlDown:()Z
       306: ifne          314
       309: aload_0
       310: iconst_1
       311: invokevirtual #354                // Method seekCursorLine:(I)V
       314: iconst_1
       315: ireturn
       316: aload_0
       317: getstatic     #272                // Field net/minecraft/client/gui/components/Whence.ABSOLUTE:Lnet/minecraft/client/gui/components/Whence;
       320: iconst_0
       321: invokevirtual #274                // Method seekCursor:(Lnet/minecraft/client/gui/components/Whence;I)V
       324: iconst_1
       325: ireturn
       326: aload_0
       327: getstatic     #357                // Field net/minecraft/client/gui/components/Whence.END:Lnet/minecraft/client/gui/components/Whence;
       330: iconst_0
       331: invokevirtual #274                // Method seekCursor:(Lnet/minecraft/client/gui/components/Whence;I)V
       334: iconst_1
       335: ireturn
       336: aload_1
       337: invokevirtual #346                // Method net/minecraft/client/input/KeyEvent.hasControlDown:()Z
       340: ifeq          354
       343: aload_0
       344: getstatic     #272                // Field net/minecraft/client/gui/components/Whence.ABSOLUTE:Lnet/minecraft/client/gui/components/Whence;
       347: iconst_0
       348: invokevirtual #274                // Method seekCursor:(Lnet/minecraft/client/gui/components/Whence;I)V
       351: goto          368
       354: aload_0
       355: getstatic     #272                // Field net/minecraft/client/gui/components/Whence.ABSOLUTE:Lnet/minecraft/client/gui/components/Whence;
       358: aload_0
       359: invokevirtual #254                // Method getCursorLineView:()Lnet/minecraft/client/gui/components/MultilineTextField$StringView;
       362: getfield      #182                // Field net/minecraft/client/gui/components/MultilineTextField$StringView.beginIndex:I
       365: invokevirtual #274                // Method seekCursor:(Lnet/minecraft/client/gui/components/Whence;I)V
       368: iconst_1
       369: ireturn
       370: aload_1
       371: invokevirtual #346                // Method net/minecraft/client/input/KeyEvent.hasControlDown:()Z
       374: ifeq          388
       377: aload_0
       378: getstatic     #357                // Field net/minecraft/client/gui/components/Whence.END:Lnet/minecraft/client/gui/components/Whence;
       381: iconst_0
       382: invokevirtual #274                // Method seekCursor:(Lnet/minecraft/client/gui/components/Whence;I)V
       385: goto          402
       388: aload_0
       389: getstatic     #272                // Field net/minecraft/client/gui/components/Whence.ABSOLUTE:Lnet/minecraft/client/gui/components/Whence;
       392: aload_0
       393: invokevirtual #254                // Method getCursorLineView:()Lnet/minecraft/client/gui/components/MultilineTextField$StringView;
       396: getfield      #185                // Field net/minecraft/client/gui/components/MultilineTextField$StringView.endIndex:I
       399: invokevirtual #274                // Method seekCursor:(Lnet/minecraft/client/gui/components/Whence;I)V
       402: iconst_1
       403: ireturn
       404: aload_1
       405: invokevirtual #346                // Method net/minecraft/client/input/KeyEvent.hasControlDown:()Z
       408: ifeq          432
       411: aload_0
       412: invokevirtual #297                // Method getPreviousWord:()Lnet/minecraft/client/gui/components/MultilineTextField$StringView;
       415: astore_2
       416: aload_0
       417: aload_2
       418: getfield      #182                // Field net/minecraft/client/gui/components/MultilineTextField$StringView.beginIndex:I
       421: aload_0
       422: getfield      #149                // Field cursor:I
       425: isub
       426: invokevirtual #359                // Method deleteText:(I)V
       429: goto          437
       432: aload_0
       433: iconst_m1
       434: invokevirtual #359                // Method deleteText:(I)V
       437: iconst_1
       438: ireturn
       439: aload_1
       440: invokevirtual #346                // Method net/minecraft/client/input/KeyEvent.hasControlDown:()Z
       443: ifeq          467
       446: aload_0
       447: invokevirtual #352                // Method getNextWord:()Lnet/minecraft/client/gui/components/MultilineTextField$StringView;
       450: astore_2
       451: aload_0
       452: aload_2
       453: getfield      #182                // Field net/minecraft/client/gui/components/MultilineTextField$StringView.beginIndex:I
       456: aload_0
       457: getfield      #149                // Field cursor:I
       460: isub
       461: invokevirtual #359                // Method deleteText:(I)V
       464: goto          472
       467: aload_0
       468: iconst_1
       469: invokevirtual #359                // Method deleteText:(I)V
       472: iconst_1
       473: ireturn
       474: aload_0
       475: ldc_w         #361                // String \n
       478: invokevirtual #204                // Method insertText:(Ljava/lang/String;)V
       481: iconst_1
       482: ireturn
       483: iconst_0
       484: ireturn

  public java.lang.Iterable<net.minecraft.client.gui.components.MultilineTextField$StringView> iterateLines();
    Code:
         0: aload_0
         1: getfield      #60                 // Field displayLines:Ljava/util/List;
         4: areturn

  public boolean hasSelection();
    Code:
         0: aload_0
         1: getfield      #151                // Field selectCursor:I
         4: aload_0
         5: getfield      #149                // Field cursor:I
         8: if_icmpeq     15
        11: iconst_1
        12: goto          16
        15: iconst_0
        16: ireturn

  public java.lang.String getSelectedText();
    Code:
         0: aload_0
         1: invokevirtual #176                // Method getSelected:()Lnet/minecraft/client/gui/components/MultilineTextField$StringView;
         4: astore_1
         5: aload_0
         6: getfield      #144                // Field value:Ljava/lang/String;
         9: aload_1
        10: getfield      #182                // Field net/minecraft/client/gui/components/MultilineTextField$StringView.beginIndex:I
        13: aload_1
        14: getfield      #185                // Field net/minecraft/client/gui/components/MultilineTextField$StringView.endIndex:I
        17: invokevirtual #258                // Method java/lang/String.substring:(II)Ljava/lang/String;
        20: areturn

  private net.minecraft.client.gui.components.MultilineTextField$StringView getCursorLineView();
    Code:
         0: aload_0
         1: iconst_0
         2: invokevirtual #265                // Method getCursorLineView:(I)Lnet/minecraft/client/gui/components/MultilineTextField$StringView;
         5: areturn

  private net.minecraft.client.gui.components.MultilineTextField$StringView getCursorLineView(int);
    Code:
         0: aload_0
         1: invokevirtual #368                // Method getLineAtCursor:()I
         4: istore_2
         5: iload_2
         6: ifge          50
         9: getstatic     #370                // Field LOGGER:Lorg/slf4j/Logger;
        12: ldc_w         #372                // String Cursor is not within text (cursor = {}, length = {})
        15: aload_0
        16: getfield      #149                // Field cursor:I
        19: invokestatic  #378                // Method java/lang/Integer.valueOf:(I)Ljava/lang/Integer;
        22: aload_0
        23: getfield      #144                // Field value:Ljava/lang/String;
        26: invokevirtual #147                // Method java/lang/String.length:()I
        29: invokestatic  #378                // Method java/lang/Integer.valueOf:(I)Ljava/lang/Integer;
        32: invokeinterface #384,  4          // InterfaceMethod org/slf4j/Logger.error:(Ljava/lang/String;Ljava/lang/Object;Ljava/lang/Object;)V
        37: aload_0
        38: getfield      #60                 // Field displayLines:Ljava/util/List;
        41: invokeinterface #388,  1          // InterfaceMethod java/util/List.getLast:()Ljava/lang/Object;
        46: checkcast     #9                  // class net/minecraft/client/gui/components/MultilineTextField$StringView
        49: areturn
        50: aload_0
        51: getfield      #60                 // Field displayLines:Ljava/util/List;
        54: iload_2
        55: iload_1
        56: iadd
        57: iconst_0
        58: aload_0
        59: getfield      #60                 // Field displayLines:Ljava/util/List;
        62: invokeinterface #226,  1          // InterfaceMethod java/util/List.size:()I
        67: iconst_1
        68: isub
        69: invokestatic  #202                // Method net/minecraft/util/Mth.clamp:(III)I
        72: invokeinterface #231,  2          // InterfaceMethod java/util/List.get:(I)Ljava/lang/Object;
        77: checkcast     #9                  // class net/minecraft/client/gui/components/MultilineTextField$StringView
        80: areturn

  public net.minecraft.client.gui.components.MultilineTextField$StringView getPreviousWord();
    Code:
         0: aload_0
         1: getfield      #144                // Field value:Ljava/lang/String;
         4: invokevirtual #160                // Method java/lang/String.isEmpty:()Z
         7: ifeq          14
        10: getstatic     #391                // Field net/minecraft/client/gui/components/MultilineTextField$StringView.EMPTY:Lnet/minecraft/client/gui/components/MultilineTextField$StringView;
        13: areturn
        14: aload_0
        15: getfield      #149                // Field cursor:I
        18: iconst_0
        19: aload_0
        20: getfield      #144                // Field value:Ljava/lang/String;
        23: invokevirtual #147                // Method java/lang/String.length:()I
        26: iconst_1
        27: isub
        28: invokestatic  #202                // Method net/minecraft/util/Mth.clamp:(III)I
        31: istore_1
        32: iload_1
        33: ifle          58
        36: aload_0
        37: getfield      #144                // Field value:Ljava/lang/String;
        40: iload_1
        41: iconst_1
        42: isub
        43: invokevirtual #395                // Method java/lang/String.charAt:(I)C
        46: invokestatic  #401                // Method java/lang/Character.isWhitespace:(C)Z
        49: ifeq          58
        52: iinc          1, -1
        55: goto          32
        58: iload_1
        59: ifle          84
        62: aload_0
        63: getfield      #144                // Field value:Ljava/lang/String;
        66: iload_1
        67: iconst_1
        68: isub
        69: invokevirtual #395                // Method java/lang/String.charAt:(I)C
        72: invokestatic  #401                // Method java/lang/Character.isWhitespace:(C)Z
        75: ifne          84
        78: iinc          1, -1
        81: goto          58
        84: new           #9                  // class net/minecraft/client/gui/components/MultilineTextField$StringView
        87: dup
        88: iload_1
        89: aload_0
        90: iload_1
        91: invokevirtual #405                // Method getWordEndPosition:(I)I
        94: invokespecial #220                // Method net/minecraft/client/gui/components/MultilineTextField$StringView."<init>":(II)V
        97: areturn

  public net.minecraft.client.gui.components.MultilineTextField$StringView getNextWord();
    Code:
         0: aload_0
         1: getfield      #144                // Field value:Ljava/lang/String;
         4: invokevirtual #160                // Method java/lang/String.isEmpty:()Z
         7: ifeq          14
        10: getstatic     #391                // Field net/minecraft/client/gui/components/MultilineTextField$StringView.EMPTY:Lnet/minecraft/client/gui/components/MultilineTextField$StringView;
        13: areturn
        14: aload_0
        15: getfield      #149                // Field cursor:I
        18: iconst_0
        19: aload_0
        20: getfield      #144                // Field value:Ljava/lang/String;
        23: invokevirtual #147                // Method java/lang/String.length:()I
        26: iconst_1
        27: isub
        28: invokestatic  #202                // Method net/minecraft/util/Mth.clamp:(III)I
        31: istore_1
        32: iload_1
        33: aload_0
        34: getfield      #144                // Field value:Ljava/lang/String;
        37: invokevirtual #147                // Method java/lang/String.length:()I
        40: if_icmpge     63
        43: aload_0
        44: getfield      #144                // Field value:Ljava/lang/String;
        47: iload_1
        48: invokevirtual #395                // Method java/lang/String.charAt:(I)C
        51: invokestatic  #401                // Method java/lang/Character.isWhitespace:(C)Z
        54: ifne          63
        57: iinc          1, 1
        60: goto          32
        63: iload_1
        64: aload_0
        65: getfield      #144                // Field value:Ljava/lang/String;
        68: invokevirtual #147                // Method java/lang/String.length:()I
        71: if_icmpge     94
        74: aload_0
        75: getfield      #144                // Field value:Ljava/lang/String;
        78: iload_1
        79: invokevirtual #395                // Method java/lang/String.charAt:(I)C
        82: invokestatic  #401                // Method java/lang/Character.isWhitespace:(C)Z
        85: ifeq          94
        88: iinc          1, 1
        91: goto          63
        94: new           #9                  // class net/minecraft/client/gui/components/MultilineTextField$StringView
        97: dup
        98: iload_1
        99: aload_0
       100: iload_1
       101: invokevirtual #405                // Method getWordEndPosition:(I)I
       104: invokespecial #220                // Method net/minecraft/client/gui/components/MultilineTextField$StringView."<init>":(II)V
       107: areturn

  private int getWordEndPosition(int);
    Code:
         0: iload_1
         1: istore_2
         2: iload_2
         3: aload_0
         4: getfield      #144                // Field value:Ljava/lang/String;
         7: invokevirtual #147                // Method java/lang/String.length:()I
        10: if_icmpge     33
        13: aload_0
        14: getfield      #144                // Field value:Ljava/lang/String;
        17: iload_2
        18: invokevirtual #395                // Method java/lang/String.charAt:(I)C
        21: invokestatic  #401                // Method java/lang/Character.isWhitespace:(C)Z
        24: ifne          33
        27: iinc          2, 1
        30: goto          2
        33: iload_2
        34: ireturn

  private void onValueChange();
    Code:
         0: aload_0
         1: invokevirtual #408                // Method reflowDisplayLines:()V
         4: aload_0
         5: getfield      #85                 // Field valueListener:Ljava/util/function/Consumer;
         8: aload_0
         9: getfield      #144                // Field value:Ljava/lang/String;
        12: invokeinterface #412,  2          // InterfaceMethod java/util/function/Consumer.accept:(Ljava/lang/Object;)V
        17: aload_0
        18: getfield      #96                 // Field cursorListener:Ljava/lang/Runnable;
        21: invokeinterface #249,  1          // InterfaceMethod java/lang/Runnable.run:()V
        26: return

  private void reflowDisplayLines();
    Code:
         0: aload_0
         1: getfield      #60                 // Field displayLines:Ljava/util/List;
         4: invokeinterface #415,  1          // InterfaceMethod java/util/List.clear:()V
         9: aload_0
        10: getfield      #144                // Field value:Ljava/lang/String;
        13: invokevirtual #160                // Method java/lang/String.isEmpty:()Z
        16: ifeq          33
        19: aload_0
        20: getfield      #60                 // Field displayLines:Ljava/util/List;
        23: getstatic     #391                // Field net/minecraft/client/gui/components/MultilineTextField$StringView.EMPTY:Lnet/minecraft/client/gui/components/MultilineTextField$StringView;
        26: invokeinterface #419,  2          // InterfaceMethod java/util/List.add:(Ljava/lang/Object;)Z
        31: pop
        32: return
        33: aload_0
        34: getfield      #98                 // Field font:Lnet/minecraft/client/gui/Font;
        37: invokevirtual #423                // Method net/minecraft/client/gui/Font.getSplitter:()Lnet/minecraft/client/StringSplitter;
        40: aload_0
        41: getfield      #144                // Field value:Ljava/lang/String;
        44: aload_0
        45: getfield      #100                // Field width:I
        48: getstatic     #428                // Field net/minecraft/network/chat/Style.EMPTY:Lnet/minecraft/network/chat/Style;
        51: iconst_0
        52: aload_0
        53: invokedynamic #437,  0            // InvokeDynamic #2:accept:(Lnet/minecraft/client/gui/components/MultilineTextField;)Lnet/minecraft/client/StringSplitter$LinePosConsumer;
        58: invokevirtual #441                // Method net/minecraft/client/StringSplitter.splitLines:(Ljava/lang/String;ILnet/minecraft/network/chat/Style;ZLnet/minecraft/client/StringSplitter$LinePosConsumer;)V
        61: aload_0
        62: getfield      #144                // Field value:Ljava/lang/String;
        65: aload_0
        66: getfield      #144                // Field value:Ljava/lang/String;
        69: invokevirtual #147                // Method java/lang/String.length:()I
        72: iconst_1
        73: isub
        74: invokevirtual #395                // Method java/lang/String.charAt:(I)C
        77: bipush        10
        79: if_icmpne     113
        82: aload_0
        83: getfield      #60                 // Field displayLines:Ljava/util/List;
        86: new           #9                  // class net/minecraft/client/gui/components/MultilineTextField$StringView
        89: dup
        90: aload_0
        91: getfield      #144                // Field value:Ljava/lang/String;
        94: invokevirtual #147                // Method java/lang/String.length:()I
        97: aload_0
        98: getfield      #144                // Field value:Ljava/lang/String;
       101: invokevirtual #147                // Method java/lang/String.length:()I
       104: invokespecial #220                // Method net/minecraft/client/gui/components/MultilineTextField$StringView."<init>":(II)V
       107: invokeinterface #419,  2          // InterfaceMethod java/util/List.add:(Ljava/lang/Object;)Z
       112: pop
       113: return

  private java.lang.String truncateFullText(java.lang.String);
    Code:
         0: aload_0
         1: invokevirtual #443                // Method hasCharacterLimit:()Z
         4: ifeq          17
         7: aload_1
         8: aload_0
         9: getfield      #62                 // Field characterLimit:I
        12: iconst_0
        13: invokestatic  #447                // Method net/minecraft/util/StringUtil.truncateStringIfNecessary:(Ljava/lang/String;IZ)Ljava/lang/String;
        16: areturn
        17: aload_1
        18: areturn

  private java.lang.String truncateInsertionText(java.lang.String);
    Code:
         0: aload_1
         1: astore_2
         2: aload_0
         3: invokevirtual #443                // Method hasCharacterLimit:()Z
         6: ifeq          29
         9: aload_0
        10: getfield      #62                 // Field characterLimit:I
        13: aload_0
        14: getfield      #144                // Field value:Ljava/lang/String;
        17: invokevirtual #147                // Method java/lang/String.length:()I
        20: isub
        21: istore_3
        22: aload_1
        23: iload_3
        24: iconst_0
        25: invokestatic  #447                // Method net/minecraft/util/StringUtil.truncateStringIfNecessary:(Ljava/lang/String;IZ)Ljava/lang/String;
        28: astore_2
        29: aload_2
        30: areturn

  private boolean overflowsLineLimit(java.lang.String);
    Code:
         0: aload_0
         1: invokevirtual #449                // Method hasLineLimit:()Z
         4: ifeq          54
         7: aload_0
         8: getfield      #98                 // Field font:Lnet/minecraft/client/gui/Font;
        11: invokevirtual #423                // Method net/minecraft/client/gui/Font.getSplitter:()Lnet/minecraft/client/StringSplitter;
        14: aload_1
        15: aload_0
        16: getfield      #100                // Field width:I
        19: getstatic     #428                // Field net/minecraft/network/chat/Style.EMPTY:Lnet/minecraft/network/chat/Style;
        22: invokevirtual #452                // Method net/minecraft/client/StringSplitter.splitLines:(Ljava/lang/String;ILnet/minecraft/network/chat/Style;)Ljava/util/List;
        25: invokeinterface #226,  1          // InterfaceMethod java/util/List.size:()I
        30: aload_1
        31: invokestatic  #455                // Method net/minecraft/util/StringUtil.endsWithNewLine:(Ljava/lang/String;)Z
        34: ifeq          41
        37: iconst_1
        38: goto          42
        41: iconst_0
        42: iadd
        43: aload_0
        44: getfield      #64                 // Field lineLimit:I
        47: if_icmple     54
        50: iconst_1
        51: goto          55
        54: iconst_0
        55: ireturn

  private void method_44416(net.minecraft.network.chat.Style, int, int);
    Code:
         0: aload_0
         1: getfield      #60                 // Field displayLines:Ljava/util/List;
         4: new           #9                  // class net/minecraft/client/gui/components/MultilineTextField$StringView
         7: dup
         8: iload_2
         9: iload_3
        10: invokespecial #220                // Method net/minecraft/client/gui/components/MultilineTextField$StringView."<init>":(II)V
        13: invokeinterface #419,  2          // InterfaceMethod java/util/List.add:(Ljava/lang/Object;)Z
        18: pop
        19: return

  private static void method_44442();
    Code:
         0: return

  private static void method_44429(java.lang.String);
    Code:
         0: return

  static {};
    Code:
         0: invokestatic  #463                // Method com/mojang/logging/LogUtils.getLogger:()Lorg/slf4j/Logger;
         3: putstatic     #370                // Field LOGGER:Lorg/slf4j/Logger;
         6: return
}
