Compiled from "BookEditScreen.java"
public class net.minecraft.client.gui.screens.inventory.BookEditScreen extends net.minecraft.client.gui.screens.Screen {
  public static final int TEXT_WIDTH;

  public static final int TEXT_HEIGHT;

  public static final int IMAGE_WIDTH;

  public static final int IMAGE_HEIGHT;

  public static final int BACKGROUND_TEXTURE_WIDTH;

  public static final int BACKGROUND_TEXTURE_HEIGHT;

  private static final net.minecraft.network.chat.Component TITLE;

  private final net.minecraft.world.entity.player.Player owner;

  private final net.minecraft.world.item.ItemStack book;

  private final net.minecraft.client.gui.screens.inventory.BookSignScreen signScreen;

  private int currentPage;

  private final java.util.List<java.lang.String> pages;

  private net.minecraft.client.gui.screens.inventory.PageButton forwardButton;

  private net.minecraft.client.gui.screens.inventory.PageButton backButton;

  private final net.minecraft.world.InteractionHand hand;

  private net.minecraft.network.chat.Component numberOfPages;

  private net.minecraft.client.gui.components.MultiLineEditBox page;

  public net.minecraft.client.gui.screens.inventory.BookEditScreen(net.minecraft.world.entity.player.Player, net.minecraft.world.item.ItemStack, net.minecraft.world.InteractionHand, net.minecraft.world.item.component.WritableBookContent);
    Code:
         0: aload_0
         1: getstatic     #61                 // Field TITLE:Lnet/minecraft/network/chat/Component;
         4: invokespecial #64                 // Method net/minecraft/client/gui/screens/Screen."<init>":(Lnet/minecraft/network/chat/Component;)V
         7: aload_0
         8: invokestatic  #70                 // Method com/google/common/collect/Lists.newArrayList:()Ljava/util/ArrayList;
        11: putfield      #72                 // Field pages:Ljava/util/List;
        14: aload_0
        15: getstatic     #77                 // Field net/minecraft/network/chat/CommonComponents.EMPTY:Lnet/minecraft/network/chat/Component;
        18: putfield      #79                 // Field numberOfPages:Lnet/minecraft/network/chat/Component;
        21: aload_0
        22: aload_1
        23: putfield      #81                 // Field owner:Lnet/minecraft/world/entity/player/Player;
        26: aload_0
        27: aload_2
        28: putfield      #83                 // Field book:Lnet/minecraft/world/item/ItemStack;
        31: aload_0
        32: aload_3
        33: putfield      #85                 // Field hand:Lnet/minecraft/world/InteractionHand;
        36: aload         4
        38: invokestatic  #91                 // Method net/minecraft/client/Minecraft.getInstance:()Lnet/minecraft/client/Minecraft;
        41: invokevirtual #95                 // Method net/minecraft/client/Minecraft.isTextFilteringEnabled:()Z
        44: invokevirtual #101                // Method net/minecraft/world/item/component/WritableBookContent.getPages:(Z)Ljava/util/stream/Stream;
        47: aload_0
        48: getfield      #72                 // Field pages:Ljava/util/List;
        51: dup
        52: invokestatic  #107                // Method java/util/Objects.requireNonNull:(Ljava/lang/Object;)Ljava/lang/Object;
        55: pop
        56: invokedynamic #129,  0            // InvokeDynamic #0:accept:(Ljava/util/List;)Ljava/util/function/Consumer;
        61: invokeinterface #135,  2          // InterfaceMethod java/util/stream/Stream.forEach:(Ljava/util/function/Consumer;)V
        66: aload_0
        67: getfield      #72                 // Field pages:Ljava/util/List;
        70: invokeinterface #138,  1          // InterfaceMethod java/util/List.isEmpty:()Z
        75: ifeq          90
        78: aload_0
        79: getfield      #72                 // Field pages:Ljava/util/List;
        82: ldc           #140                // String
        84: invokeinterface #115,  2          // InterfaceMethod java/util/List.add:(Ljava/lang/Object;)Z
        89: pop
        90: aload_0
        91: new           #146                // class net/minecraft/client/gui/screens/inventory/BookSignScreen
        94: dup
        95: aload_0
        96: aload_1
        97: aload_3
        98: aload_0
        99: getfield      #72                 // Field pages:Ljava/util/List;
       102: invokespecial #149                // Method net/minecraft/client/gui/screens/inventory/BookSignScreen."<init>":(Lnet/minecraft/client/gui/screens/inventory/BookEditScreen;Lnet/minecraft/world/entity/player/Player;Lnet/minecraft/world/InteractionHand;Ljava/util/List;)V
       105: putfield      #151                // Field signScreen:Lnet/minecraft/client/gui/screens/inventory/BookSignScreen;
       108: return

  private int getNumPages();
    Code:
         0: aload_0
         1: getfield      #72                 // Field pages:Ljava/util/List;
         4: invokeinterface #159,  1          // InterfaceMethod java/util/List.size:()I
         9: ireturn

  protected void init();
    Code:
         0: aload_0
         1: getfield      #164                // Field width:I
         4: sipush        192
         7: isub
         8: iconst_2
         9: idiv
        10: istore_1
        11: iconst_2
        12: istore_2
        13: bipush        8
        15: istore_3
        16: aload_0
        17: invokestatic  #168                // Method net/minecraft/client/gui/components/MultiLineEditBox.builder:()Lnet/minecraft/client/gui/components/MultiLineEditBox$Builder;
        20: iconst_0
        21: invokevirtual #172                // Method net/minecraft/client/gui/components/MultiLineEditBox$Builder.setShowDecorations:(Z)Lnet/minecraft/client/gui/components/MultiLineEditBox$Builder;
        24: ldc           #173                // int -16777216
        26: invokevirtual #177                // Method net/minecraft/client/gui/components/MultiLineEditBox$Builder.setTextColor:(I)Lnet/minecraft/client/gui/components/MultiLineEditBox$Builder;
        29: ldc           #173                // int -16777216
        31: invokevirtual #180                // Method net/minecraft/client/gui/components/MultiLineEditBox$Builder.setCursorColor:(I)Lnet/minecraft/client/gui/components/MultiLineEditBox$Builder;
        34: iconst_0
        35: invokevirtual #183                // Method net/minecraft/client/gui/components/MultiLineEditBox$Builder.setShowBackground:(Z)Lnet/minecraft/client/gui/components/MultiLineEditBox$Builder;
        38: iconst_0
        39: invokevirtual #186                // Method net/minecraft/client/gui/components/MultiLineEditBox$Builder.setTextShadow:(Z)Lnet/minecraft/client/gui/components/MultiLineEditBox$Builder;
        42: aload_0
        43: getfield      #164                // Field width:I
        46: bipush        114
        48: isub
        49: iconst_2
        50: idiv
        51: bipush        8
        53: isub
        54: invokevirtual #189                // Method net/minecraft/client/gui/components/MultiLineEditBox$Builder.setX:(I)Lnet/minecraft/client/gui/components/MultiLineEditBox$Builder;
        57: bipush        28
        59: invokevirtual #192                // Method net/minecraft/client/gui/components/MultiLineEditBox$Builder.setY:(I)Lnet/minecraft/client/gui/components/MultiLineEditBox$Builder;
        62: aload_0
        63: getfield      #196                // Field font:Lnet/minecraft/client/gui/Font;
        66: bipush        122
        68: sipush        134
        71: getstatic     #77                 // Field net/minecraft/network/chat/CommonComponents.EMPTY:Lnet/minecraft/network/chat/Component;
        74: invokevirtual #200                // Method net/minecraft/client/gui/components/MultiLineEditBox$Builder.build:(Lnet/minecraft/client/gui/Font;IILnet/minecraft/network/chat/Component;)Lnet/minecraft/client/gui/components/MultiLineEditBox;
        77: putfield      #202                // Field page:Lnet/minecraft/client/gui/components/MultiLineEditBox;
        80: aload_0
        81: getfield      #202                // Field page:Lnet/minecraft/client/gui/components/MultiLineEditBox;
        84: sipush        1024
        87: invokevirtual #206                // Method net/minecraft/client/gui/components/MultiLineEditBox.setCharacterLimit:(I)V
        90: aload_0
        91: getfield      #202                // Field page:Lnet/minecraft/client/gui/components/MultiLineEditBox;
        94: bipush        126
        96: aload_0
        97: getfield      #196                // Field font:Lnet/minecraft/client/gui/Font;
       100: invokestatic  #107                // Method java/util/Objects.requireNonNull:(Ljava/lang/Object;)Ljava/lang/Object;
       103: pop
       104: bipush        9
       106: idiv
       107: invokevirtual #209                // Method net/minecraft/client/gui/components/MultiLineEditBox.setLineLimit:(I)V
       110: aload_0
       111: getfield      #202                // Field page:Lnet/minecraft/client/gui/components/MultiLineEditBox;
       114: aload_0
       115: invokedynamic #216,  0            // InvokeDynamic #1:accept:(Lnet/minecraft/client/gui/screens/inventory/BookEditScreen;)Ljava/util/function/Consumer;
       120: invokevirtual #219                // Method net/minecraft/client/gui/components/MultiLineEditBox.setValueListener:(Ljava/util/function/Consumer;)V
       123: aload_0
       124: aload_0
       125: getfield      #202                // Field page:Lnet/minecraft/client/gui/components/MultiLineEditBox;
       128: invokevirtual #223                // Method addRenderableWidget:(Lnet/minecraft/client/gui/components/events/GuiEventListener;)Lnet/minecraft/client/gui/components/events/GuiEventListener;
       131: pop
       132: aload_0
       133: invokevirtual #226                // Method updatePageContent:()V
       136: aload_0
       137: aload_0
       138: invokevirtual #230                // Method getPageNumberMessage:()Lnet/minecraft/network/chat/Component;
       141: putfield      #79                 // Field numberOfPages:Lnet/minecraft/network/chat/Component;
       144: aload_0
       145: aload_0
       146: new           #232                // class net/minecraft/client/gui/screens/inventory/PageButton
       149: dup
       150: iload_1
       151: bipush        43
       153: iadd
       154: sipush        159
       157: iconst_0
       158: aload_0
       159: invokedynamic #242,  0            // InvokeDynamic #2:onPress:(Lnet/minecraft/client/gui/screens/inventory/BookEditScreen;)Lnet/minecraft/client/gui/components/Button$OnPress;
       164: iconst_1
       165: invokespecial #245                // Method net/minecraft/client/gui/screens/inventory/PageButton."<init>":(IIZLnet/minecraft/client/gui/components/Button$OnPress;Z)V
       168: invokevirtual #223                // Method addRenderableWidget:(Lnet/minecraft/client/gui/components/events/GuiEventListener;)Lnet/minecraft/client/gui/components/events/GuiEventListener;
       171: checkcast     #232                // class net/minecraft/client/gui/screens/inventory/PageButton
       174: putfield      #247                // Field backButton:Lnet/minecraft/client/gui/screens/inventory/PageButton;
       177: aload_0
       178: aload_0
       179: new           #232                // class net/minecraft/client/gui/screens/inventory/PageButton
       182: dup
       183: iload_1
       184: bipush        116
       186: iadd
       187: sipush        159
       190: iconst_1
       191: aload_0
       192: invokedynamic #252,  0            // InvokeDynamic #3:onPress:(Lnet/minecraft/client/gui/screens/inventory/BookEditScreen;)Lnet/minecraft/client/gui/components/Button$OnPress;
       197: iconst_1
       198: invokespecial #245                // Method net/minecraft/client/gui/screens/inventory/PageButton."<init>":(IIZLnet/minecraft/client/gui/components/Button$OnPress;Z)V
       201: invokevirtual #223                // Method addRenderableWidget:(Lnet/minecraft/client/gui/components/events/GuiEventListener;)Lnet/minecraft/client/gui/components/events/GuiEventListener;
       204: checkcast     #232                // class net/minecraft/client/gui/screens/inventory/PageButton
       207: putfield      #254                // Field forwardButton:Lnet/minecraft/client/gui/screens/inventory/PageButton;
       210: aload_0
       211: ldc_w         #256                // String book.signButton
       214: invokestatic  #262                // InterfaceMethod net/minecraft/network/chat/Component.translatable:(Ljava/lang/String;)Lnet/minecraft/network/chat/MutableComponent;
       217: aload_0
       218: invokedynamic #267,  0            // InvokeDynamic #4:onPress:(Lnet/minecraft/client/gui/screens/inventory/BookEditScreen;)Lnet/minecraft/client/gui/components/Button$OnPress;
       223: invokestatic  #270                // Method net/minecraft/client/gui/components/Button.builder:(Lnet/minecraft/network/chat/Component;Lnet/minecraft/client/gui/components/Button$OnPress;)Lnet/minecraft/client/gui/components/Button$Builder;
       226: aload_0
       227: getfield      #164                // Field width:I
       230: iconst_2
       231: idiv
       232: bipush        100
       234: isub
       235: sipush        196
       238: bipush        98
       240: bipush        20
       242: invokevirtual #274                // Method net/minecraft/client/gui/components/Button$Builder.bounds:(IIII)Lnet/minecraft/client/gui/components/Button$Builder;
       245: invokevirtual #277                // Method net/minecraft/client/gui/components/Button$Builder.build:()Lnet/minecraft/client/gui/components/Button;
       248: invokevirtual #223                // Method addRenderableWidget:(Lnet/minecraft/client/gui/components/events/GuiEventListener;)Lnet/minecraft/client/gui/components/events/GuiEventListener;
       251: pop
       252: aload_0
       253: getstatic     #280                // Field net/minecraft/network/chat/CommonComponents.GUI_DONE:Lnet/minecraft/network/chat/Component;
       256: aload_0
       257: invokedynamic #285,  0            // InvokeDynamic #5:onPress:(Lnet/minecraft/client/gui/screens/inventory/BookEditScreen;)Lnet/minecraft/client/gui/components/Button$OnPress;
       262: invokestatic  #270                // Method net/minecraft/client/gui/components/Button.builder:(Lnet/minecraft/network/chat/Component;Lnet/minecraft/client/gui/components/Button$OnPress;)Lnet/minecraft/client/gui/components/Button$Builder;
       265: aload_0
       266: getfield      #164                // Field width:I
       269: iconst_2
       270: idiv
       271: iconst_2
       272: iadd
       273: sipush        196
       276: bipush        98
       278: bipush        20
       280: invokevirtual #274                // Method net/minecraft/client/gui/components/Button$Builder.bounds:(IIII)Lnet/minecraft/client/gui/components/Button$Builder;
       283: invokevirtual #277                // Method net/minecraft/client/gui/components/Button$Builder.build:()Lnet/minecraft/client/gui/components/Button;
       286: invokevirtual #223                // Method addRenderableWidget:(Lnet/minecraft/client/gui/components/events/GuiEventListener;)Lnet/minecraft/client/gui/components/events/GuiEventListener;
       289: pop
       290: aload_0
       291: invokevirtual #288                // Method updateButtonVisibility:()V
       294: return

  protected void setInitialFocus();
    Code:
         0: aload_0
         1: aload_0
         2: getfield      #202                // Field page:Lnet/minecraft/client/gui/components/MultiLineEditBox;
         5: invokevirtual #295                // Method setInitialFocus:(Lnet/minecraft/client/gui/components/events/GuiEventListener;)V
         8: return

  public net.minecraft.network.chat.Component getNarrationMessage();
    Code:
         0: iconst_2
         1: anewarray     #258                // class net/minecraft/network/chat/Component
         4: dup
         5: iconst_0
         6: aload_0
         7: invokespecial #298                // Method net/minecraft/client/gui/screens/Screen.getNarrationMessage:()Lnet/minecraft/network/chat/Component;
        10: aastore
        11: dup
        12: iconst_1
        13: aload_0
        14: invokevirtual #230                // Method getPageNumberMessage:()Lnet/minecraft/network/chat/Component;
        17: aastore
        18: invokestatic  #302                // Method net/minecraft/network/chat/CommonComponents.joinForNarration:([Lnet/minecraft/network/chat/Component;)Lnet/minecraft/network/chat/MutableComponent;
        21: areturn

  private net.minecraft.network.chat.Component getPageNumberMessage();
    Code:
         0: ldc_w         #304                // String book.pageIndicator
         3: iconst_2
         4: anewarray     #306                // class java/lang/Object
         7: dup
         8: iconst_0
         9: aload_0
        10: getfield      #308                // Field currentPage:I
        13: iconst_1
        14: iadd
        15: invokestatic  #314                // Method java/lang/Integer.valueOf:(I)Ljava/lang/Integer;
        18: aastore
        19: dup
        20: iconst_1
        21: aload_0
        22: invokevirtual #316                // Method getNumPages:()I
        25: invokestatic  #314                // Method java/lang/Integer.valueOf:(I)Ljava/lang/Integer;
        28: aastore
        29: invokestatic  #319                // InterfaceMethod net/minecraft/network/chat/Component.translatable:(Ljava/lang/String;[Ljava/lang/Object;)Lnet/minecraft/network/chat/MutableComponent;
        32: areturn

  private void pageBack();
    Code:
         0: aload_0
         1: getfield      #308                // Field currentPage:I
         4: ifle          21
         7: aload_0
         8: dup
         9: getfield      #308                // Field currentPage:I
        12: iconst_1
        13: isub
        14: putfield      #308                // Field currentPage:I
        17: aload_0
        18: invokevirtual #226                // Method updatePageContent:()V
        21: aload_0
        22: invokevirtual #288                // Method updateButtonVisibility:()V
        25: return

  private void pageForward();
    Code:
         0: aload_0
         1: getfield      #308                // Field currentPage:I
         4: aload_0
         5: invokevirtual #316                // Method getNumPages:()I
         8: iconst_1
         9: isub
        10: if_icmpge     26
        13: aload_0
        14: dup
        15: getfield      #308                // Field currentPage:I
        18: iconst_1
        19: iadd
        20: putfield      #308                // Field currentPage:I
        23: goto          53
        26: aload_0
        27: invokevirtual #324                // Method appendPageToBook:()V
        30: aload_0
        31: getfield      #308                // Field currentPage:I
        34: aload_0
        35: invokevirtual #316                // Method getNumPages:()I
        38: iconst_1
        39: isub
        40: if_icmpge     53
        43: aload_0
        44: dup
        45: getfield      #308                // Field currentPage:I
        48: iconst_1
        49: iadd
        50: putfield      #308                // Field currentPage:I
        53: aload_0
        54: invokevirtual #226                // Method updatePageContent:()V
        57: aload_0
        58: invokevirtual #288                // Method updateButtonVisibility:()V
        61: return

  private void updatePageContent();
    Code:
         0: aload_0
         1: getfield      #202                // Field page:Lnet/minecraft/client/gui/components/MultiLineEditBox;
         4: aload_0
         5: getfield      #72                 // Field pages:Ljava/util/List;
         8: aload_0
         9: getfield      #308                // Field currentPage:I
        12: invokeinterface #328,  2          // InterfaceMethod java/util/List.get:(I)Ljava/lang/Object;
        17: checkcast     #330                // class java/lang/String
        20: iconst_1
        21: invokevirtual #334                // Method net/minecraft/client/gui/components/MultiLineEditBox.setValue:(Ljava/lang/String;Z)V
        24: aload_0
        25: aload_0
        26: invokevirtual #230                // Method getPageNumberMessage:()Lnet/minecraft/network/chat/Component;
        29: putfield      #79                 // Field numberOfPages:Lnet/minecraft/network/chat/Component;
        32: return

  private void updateButtonVisibility();
    Code:
         0: aload_0
         1: getfield      #247                // Field backButton:Lnet/minecraft/client/gui/screens/inventory/PageButton;
         4: aload_0
         5: getfield      #308                // Field currentPage:I
         8: ifle          15
        11: iconst_1
        12: goto          16
        15: iconst_0
        16: putfield      #338                // Field net/minecraft/client/gui/screens/inventory/PageButton.visible:Z
        19: return

  private void eraseEmptyTrailingPages();
    Code:
         0: aload_0
         1: getfield      #72                 // Field pages:Ljava/util/List;
         4: aload_0
         5: getfield      #72                 // Field pages:Ljava/util/List;
         8: invokeinterface #159,  1          // InterfaceMethod java/util/List.size:()I
        13: invokeinterface #343,  2          // InterfaceMethod java/util/List.listIterator:(I)Ljava/util/ListIterator;
        18: astore_1
        19: aload_1
        20: invokeinterface #348,  1          // InterfaceMethod java/util/ListIterator.hasPrevious:()Z
        25: ifeq          52
        28: aload_1
        29: invokeinterface #352,  1          // InterfaceMethod java/util/ListIterator.previous:()Ljava/lang/Object;
        34: checkcast     #330                // class java/lang/String
        37: invokevirtual #353                // Method java/lang/String.isEmpty:()Z
        40: ifeq          52
        43: aload_1
        44: invokeinterface #356,  1          // InterfaceMethod java/util/ListIterator.remove:()V
        49: goto          19
        52: return

  private void saveChanges();
    Code:
         0: aload_0
         1: invokevirtual #361                // Method eraseEmptyTrailingPages:()V
         4: aload_0
         5: invokevirtual #364                // Method updateLocalCopy:()V
         8: aload_0
         9: getfield      #85                 // Field hand:Lnet/minecraft/world/InteractionHand;
        12: getstatic     #367                // Field net/minecraft/world/InteractionHand.MAIN_HAND:Lnet/minecraft/world/InteractionHand;
        15: if_acmpne     31
        18: aload_0
        19: getfield      #81                 // Field owner:Lnet/minecraft/world/entity/player/Player;
        22: invokevirtual #371                // Method net/minecraft/world/entity/player/Player.getInventory:()Lnet/minecraft/world/entity/player/Inventory;
        25: invokevirtual #376                // Method net/minecraft/world/entity/player/Inventory.getSelectedSlot:()I
        28: goto          33
        31: bipush        40
        33: istore_1
        34: aload_0
        35: getfield      #380                // Field minecraft:Lnet/minecraft/client/Minecraft;
        38: invokevirtual #384                // Method net/minecraft/client/Minecraft.getConnection:()Lnet/minecraft/client/multiplayer/ClientPacketListener;
        41: new           #386                // class net/minecraft/network/protocol/game/ServerboundEditBookPacket
        44: dup
        45: iload_1
        46: aload_0
        47: getfield      #72                 // Field pages:Ljava/util/List;
        50: invokestatic  #392                // Method java/util/Optional.empty:()Ljava/util/Optional;
        53: invokespecial #395                // Method net/minecraft/network/protocol/game/ServerboundEditBookPacket."<init>":(ILjava/util/List;Ljava/util/Optional;)V
        56: invokevirtual #401                // Method net/minecraft/client/multiplayer/ClientPacketListener.send:(Lnet/minecraft/network/protocol/Packet;)V
        59: return

  private void updateLocalCopy();
    Code:
         0: aload_0
         1: getfield      #83                 // Field book:Lnet/minecraft/world/item/ItemStack;
         4: getstatic     #407                // Field net/minecraft/core/component/DataComponents.WRITABLE_BOOK_CONTENT:Lnet/minecraft/core/component/DataComponentType;
         7: new           #97                 // class net/minecraft/world/item/component/WritableBookContent
        10: dup
        11: aload_0
        12: getfield      #72                 // Field pages:Ljava/util/List;
        15: invokeinterface #411,  1          // InterfaceMethod java/util/List.stream:()Ljava/util/stream/Stream;
        20: invokedynamic #425,  0            // InvokeDynamic #6:apply:()Ljava/util/function/Function;
        25: invokeinterface #429,  2          // InterfaceMethod java/util/stream/Stream.map:(Ljava/util/function/Function;)Ljava/util/stream/Stream;
        30: invokeinterface #433,  1          // InterfaceMethod java/util/stream/Stream.toList:()Ljava/util/List;
        35: invokespecial #436                // Method net/minecraft/world/item/component/WritableBookContent."<init>":(Ljava/util/List;)V
        38: invokevirtual #442                // Method net/minecraft/world/item/ItemStack.set:(Lnet/minecraft/core/component/DataComponentType;Ljava/lang/Object;)Ljava/lang/Object;
        41: pop
        42: return

  private void appendPageToBook();
    Code:
         0: aload_0
         1: invokevirtual #316                // Method getNumPages:()I
         4: bipush        100
         6: if_icmplt     10
         9: return
        10: aload_0
        11: getfield      #72                 // Field pages:Ljava/util/List;
        14: ldc           #140                // String
        16: invokeinterface #115,  2          // InterfaceMethod java/util/List.add:(Ljava/lang/Object;)Z
        21: pop
        22: return

  public boolean isInGameUi();
    Code:
         0: iconst_1
         1: ireturn

  public boolean keyPressed(net.minecraft.client.input.KeyEvent);
    Code:
         0: aload_1
         1: invokevirtual #451                // Method net/minecraft/client/input/KeyEvent.key:()I
         4: lookupswitch  { // 2

                     266: 32

                     267: 42
                 default: 52
            }
        32: aload_0
        33: getfield      #247                // Field backButton:Lnet/minecraft/client/gui/screens/inventory/PageButton;
        36: aload_1
        37: invokevirtual #454                // Method net/minecraft/client/gui/screens/inventory/PageButton.onPress:(Lnet/minecraft/client/input/InputWithModifiers;)V
        40: iconst_1
        41: ireturn
        42: aload_0
        43: getfield      #254                // Field forwardButton:Lnet/minecraft/client/gui/screens/inventory/PageButton;
        46: aload_1
        47: invokevirtual #454                // Method net/minecraft/client/gui/screens/inventory/PageButton.onPress:(Lnet/minecraft/client/input/InputWithModifiers;)V
        50: iconst_1
        51: ireturn
        52: aload_0
        53: aload_1
        54: invokespecial #456                // Method net/minecraft/client/gui/screens/Screen.keyPressed:(Lnet/minecraft/client/input/KeyEvent;)Z
        57: ireturn

  public void render(net.minecraft.client.gui.GuiGraphics, int, int, float);
    Code:
         0: aload_0
         1: aload_1
         2: iload_2
         3: iload_3
         4: fload         4
         6: invokespecial #463                // Method net/minecraft/client/gui/screens/Screen.render:(Lnet/minecraft/client/gui/GuiGraphics;IIF)V
         9: aload_0
        10: getfield      #164                // Field width:I
        13: sipush        192
        16: isub
        17: iconst_2
        18: idiv
        19: istore        5
        21: iconst_2
        22: istore        6
        24: aload_0
        25: getfield      #196                // Field font:Lnet/minecraft/client/gui/Font;
        28: aload_0
        29: getfield      #79                 // Field numberOfPages:Lnet/minecraft/network/chat/Component;
        32: invokevirtual #468                // Method net/minecraft/client/gui/Font.width:(Lnet/minecraft/network/chat/FormattedText;)I
        35: istore        7
        37: aload_1
        38: aload_0
        39: getfield      #196                // Field font:Lnet/minecraft/client/gui/Font;
        42: aload_0
        43: getfield      #79                 // Field numberOfPages:Lnet/minecraft/network/chat/Component;
        46: iload         5
        48: iload         7
        50: isub
        51: sipush        192
        54: iadd
        55: bipush        44
        57: isub
        58: bipush        18
        60: ldc           #173                // int -16777216
        62: iconst_0
        63: invokevirtual #474                // Method net/minecraft/client/gui/GuiGraphics.drawString:(Lnet/minecraft/client/gui/Font;Lnet/minecraft/network/chat/Component;IIIZ)V
        66: return

  public void renderBackground(net.minecraft.client.gui.GuiGraphics, int, int, float);
    Code:
         0: aload_0
         1: aload_1
         2: iload_2
         3: iload_3
         4: fload         4
         6: invokespecial #481                // Method net/minecraft/client/gui/screens/Screen.renderBackground:(Lnet/minecraft/client/gui/GuiGraphics;IIF)V
         9: aload_1
        10: getstatic     #487                // Field net/minecraft/client/renderer/RenderPipelines.GUI_TEXTURED:Lcom/mojang/blaze3d/pipeline/RenderPipeline;
        13: getstatic     #493                // Field net/minecraft/client/gui/screens/inventory/BookViewScreen.BOOK_LOCATION:Lnet/minecraft/resources/ResourceLocation;
        16: aload_0
        17: getfield      #164                // Field width:I
        20: sipush        192
        23: isub
        24: iconst_2
        25: idiv
        26: iconst_2
        27: fconst_0
        28: fconst_0
        29: sipush        192
        32: sipush        192
        35: sipush        256
        38: sipush        256
        41: invokevirtual #497                // Method net/minecraft/client/gui/GuiGraphics.blit:(Lcom/mojang/blaze3d/pipeline/RenderPipeline;Lnet/minecraft/resources/ResourceLocation;IIFFIIII)V
        44: return

  private void method_19882(net.minecraft.client.gui.components.Button);
    Code:
         0: aload_0
         1: getfield      #380                // Field minecraft:Lnet/minecraft/client/Minecraft;
         4: aconst_null
         5: invokevirtual #502                // Method net/minecraft/client/Minecraft.setScreen:(Lnet/minecraft/client/gui/screens/Screen;)V
         8: aload_0
         9: invokevirtual #504                // Method saveChanges:()V
        12: return

  private void method_19881(net.minecraft.client.gui.components.Button);
    Code:
         0: aload_0
         1: getfield      #380                // Field minecraft:Lnet/minecraft/client/Minecraft;
         4: aload_0
         5: getfield      #151                // Field signScreen:Lnet/minecraft/client/gui/screens/inventory/BookSignScreen;
         8: invokevirtual #502                // Method net/minecraft/client/Minecraft.setScreen:(Lnet/minecraft/client/gui/screens/Screen;)V
        11: return

  private void method_19879(net.minecraft.client.gui.components.Button);
    Code:
         0: aload_0
         1: invokevirtual #507                // Method pageForward:()V
         4: return

  private void method_19878(net.minecraft.client.gui.components.Button);
    Code:
         0: aload_0
         1: invokevirtual #509                // Method pageBack:()V
         4: return

  private void method_71539(java.lang.String);
    Code:
         0: aload_0
         1: getfield      #72                 // Field pages:Ljava/util/List;
         4: aload_0
         5: getfield      #308                // Field currentPage:I
         8: aload_1
         9: invokeinterface #513,  3          // InterfaceMethod java/util/List.set:(ILjava/lang/Object;)Ljava/lang/Object;
        14: pop
        15: return

  static {};
    Code:
         0: ldc_w         #517                // String book.edit.title
         3: invokestatic  #262                // InterfaceMethod net/minecraft/network/chat/Component.translatable:(Ljava/lang/String;)Lnet/minecraft/network/chat/MutableComponent;
         6: putstatic     #61                 // Field TITLE:Lnet/minecraft/network/chat/Component;
         9: return
}
