Compiled from "Font.java"
public class net.minecraft.client.gui.Font {
  private static final float EFFECT_DEPTH;

  private static final float OVER_EFFECT_DEPTH;

  private static final float UNDER_EFFECT_DEPTH;

  public static final float SHADOW_DEPTH;

  public static final int NO_SHADOW;

  public final int lineHeight;

  private final net.minecraft.util.RandomSource random;

  final net.minecraft.client.gui.Font$Provider provider;

  private final net.minecraft.client.StringSplitter splitter;

  public net.minecraft.client.gui.Font(net.minecraft.client.gui.Font$Provider);
    Code:
         0: aload_0
         1: invokespecial #56                 // Method java/lang/Object."<init>":()V
         4: aload_0
         5: bipush        9
         7: putfield      #58                 // Field lineHeight:I
        10: aload_0
        11: invokestatic  #64                 // InterfaceMethod net/minecraft/util/RandomSource.create:()Lnet/minecraft/util/RandomSource;
        14: putfield      #66                 // Field random:Lnet/minecraft/util/RandomSource;
        17: aload_0
        18: aload_1
        19: putfield      #68                 // Field provider:Lnet/minecraft/client/gui/Font$Provider;
        22: aload_0
        23: new           #22                 // class net/minecraft/client/StringSplitter
        26: dup
        27: aload_0
        28: invokedynamic #85,  0             // InvokeDynamic #0:getWidth:(Lnet/minecraft/client/gui/Font;)Lnet/minecraft/client/StringSplitter$WidthProvider;
        33: invokespecial #88                 // Method net/minecraft/client/StringSplitter."<init>":(Lnet/minecraft/client/StringSplitter$WidthProvider;)V
        36: putfield      #90                 // Field splitter:Lnet/minecraft/client/StringSplitter;
        39: return

  private net.minecraft.client.gui.GlyphSource getGlyphSource(net.minecraft.network.chat.FontDescription);
    Code:
         0: aload_0
         1: getfield      #68                 // Field provider:Lnet/minecraft/client/gui/Font$Provider;
         4: aload_1
         5: invokeinterface #98,  2           // InterfaceMethod net/minecraft/client/gui/Font$Provider.glyphs:(Lnet/minecraft/network/chat/FontDescription;)Lnet/minecraft/client/gui/GlyphSource;
        10: areturn

  public java.lang.String bidirectionalShaping(java.lang.String);
    Code:
         0: new           #106                // class com/ibm/icu/text/Bidi
         3: dup
         4: new           #108                // class com/ibm/icu/text/ArabicShaping
         7: dup
         8: bipush        8
        10: invokespecial #111                // Method com/ibm/icu/text/ArabicShaping."<init>":(I)V
        13: aload_1
        14: invokevirtual #114                // Method com/ibm/icu/text/ArabicShaping.shape:(Ljava/lang/String;)Ljava/lang/String;
        17: bipush        127
        19: invokespecial #117                // Method com/ibm/icu/text/Bidi."<init>":(Ljava/lang/String;I)V
        22: astore_2
        23: aload_2
        24: iconst_0
        25: invokevirtual #120                // Method com/ibm/icu/text/Bidi.setReorderingMode:(I)V
        28: aload_2
        29: iconst_2
        30: invokevirtual #124                // Method com/ibm/icu/text/Bidi.writeReordered:(I)Ljava/lang/String;
        33: areturn
        34: astore_2
        35: aload_1
        36: areturn
      Exception table:
         from    to  target type
             0    33    34   Class com/ibm/icu/text/ArabicShapingException

  public void drawInBatch(java.lang.String, float, float, int, boolean, org.joml.Matrix4f, net.minecraft.client.renderer.MultiBufferSource, net.minecraft.client.gui.Font$DisplayMode, int, int);
    Code:
         0: aload_0
         1: aload_1
         2: fload_2
         3: fload_3
         4: iload         4
         6: iload         5
         8: iload         9
        10: invokevirtual #144                // Method prepareText:(Ljava/lang/String;FFIZI)Lnet/minecraft/client/gui/Font$PreparedText;
        13: astore        11
        15: aload         11
        17: aload         7
        19: aload         6
        21: aload         8
        23: iload         10
        25: invokestatic  #148                // InterfaceMethod net/minecraft/client/gui/Font$GlyphVisitor.forMultiBufferSource:(Lnet/minecraft/client/renderer/MultiBufferSource;Lorg/joml/Matrix4f;Lnet/minecraft/client/gui/Font$DisplayMode;I)Lnet/minecraft/client/gui/Font$GlyphVisitor;
        28: invokeinterface #152,  2          // InterfaceMethod net/minecraft/client/gui/Font$PreparedText.visit:(Lnet/minecraft/client/gui/Font$GlyphVisitor;)V
        33: return

  public void drawInBatch(net.minecraft.network.chat.Component, float, float, int, boolean, org.joml.Matrix4f, net.minecraft.client.renderer.MultiBufferSource, net.minecraft.client.gui.Font$DisplayMode, int, int);
    Code:
         0: aload_0
         1: aload_1
         2: invokeinterface #166,  1          // InterfaceMethod net/minecraft/network/chat/Component.getVisualOrderText:()Lnet/minecraft/util/FormattedCharSequence;
         7: fload_2
         8: fload_3
         9: iload         4
        11: iload         5
        13: iload         9
        15: invokevirtual #169                // Method prepareText:(Lnet/minecraft/util/FormattedCharSequence;FFIZI)Lnet/minecraft/client/gui/Font$PreparedText;
        18: astore        11
        20: aload         11
        22: aload         7
        24: aload         6
        26: aload         8
        28: iload         10
        30: invokestatic  #148                // InterfaceMethod net/minecraft/client/gui/Font$GlyphVisitor.forMultiBufferSource:(Lnet/minecraft/client/renderer/MultiBufferSource;Lorg/joml/Matrix4f;Lnet/minecraft/client/gui/Font$DisplayMode;I)Lnet/minecraft/client/gui/Font$GlyphVisitor;
        33: invokeinterface #152,  2          // InterfaceMethod net/minecraft/client/gui/Font$PreparedText.visit:(Lnet/minecraft/client/gui/Font$GlyphVisitor;)V
        38: return

  public void drawInBatch(net.minecraft.util.FormattedCharSequence, float, float, int, boolean, org.joml.Matrix4f, net.minecraft.client.renderer.MultiBufferSource, net.minecraft.client.gui.Font$DisplayMode, int, int);
    Code:
         0: aload_0
         1: aload_1
         2: fload_2
         3: fload_3
         4: iload         4
         6: iload         5
         8: iload         9
        10: invokevirtual #169                // Method prepareText:(Lnet/minecraft/util/FormattedCharSequence;FFIZI)Lnet/minecraft/client/gui/Font$PreparedText;
        13: astore        11
        15: aload         11
        17: aload         7
        19: aload         6
        21: aload         8
        23: iload         10
        25: invokestatic  #148                // InterfaceMethod net/minecraft/client/gui/Font$GlyphVisitor.forMultiBufferSource:(Lnet/minecraft/client/renderer/MultiBufferSource;Lorg/joml/Matrix4f;Lnet/minecraft/client/gui/Font$DisplayMode;I)Lnet/minecraft/client/gui/Font$GlyphVisitor;
        28: invokeinterface #152,  2          // InterfaceMethod net/minecraft/client/gui/Font$PreparedText.visit:(Lnet/minecraft/client/gui/Font$GlyphVisitor;)V
        33: return

  public void drawInBatch8xOutline(net.minecraft.util.FormattedCharSequence, float, float, int, int, org.joml.Matrix4f, net.minecraft.client.renderer.MultiBufferSource, int);
    Code:
         0: new           #13                 // class net/minecraft/client/gui/Font$PreparedTextBuilder
         3: dup
         4: aload_0
         5: fconst_0
         6: fconst_0
         7: iload         5
         9: iconst_0
        10: invokespecial #178                // Method net/minecraft/client/gui/Font$PreparedTextBuilder."<init>":(Lnet/minecraft/client/gui/Font;FFIZ)V
        13: astore        9
        15: iconst_m1
        16: istore        10
        18: iload         10
        20: iconst_1
        21: if_icmpgt     96
        24: iconst_m1
        25: istore        11
        27: iload         11
        29: iconst_1
        30: if_icmpgt     90
        33: iload         10
        35: ifne          43
        38: iload         11
        40: ifeq          84
        43: iconst_1
        44: newarray       float
        46: dup
        47: iconst_0
        48: fload_2
        49: fastore
        50: astore        12
        52: iload         10
        54: istore        13
        56: iload         11
        58: istore        14
        60: aload_1
        61: aload_0
        62: aload         9
        64: aload         12
        66: iload         13
        68: fload_3
        69: iload         14
        71: iload         5
        73: invokedynamic #189,  0            // InvokeDynamic #1:accept:(Lnet/minecraft/client/gui/Font;Lnet/minecraft/client/gui/Font$PreparedTextBuilder;[FIFII)Lnet/minecraft/util/FormattedCharSink;
        78: invokeinterface #194,  2          // InterfaceMethod net/minecraft/util/FormattedCharSequence.accept:(Lnet/minecraft/util/FormattedCharSink;)Z
        83: pop
        84: iinc          11, 1
        87: goto          27
        90: iinc          10, 1
        93: goto          18
        96: aload         7
        98: aload         6
       100: getstatic     #201                // Field net/minecraft/client/gui/Font$DisplayMode.NORMAL:Lnet/minecraft/client/gui/Font$DisplayMode;
       103: iload         8
       105: invokestatic  #148                // InterfaceMethod net/minecraft/client/gui/Font$GlyphVisitor.forMultiBufferSource:(Lnet/minecraft/client/renderer/MultiBufferSource;Lorg/joml/Matrix4f;Lnet/minecraft/client/gui/Font$DisplayMode;I)Lnet/minecraft/client/gui/Font$GlyphVisitor;
       108: astore        10
       110: aload         9
       112: getfield      #204                // Field net/minecraft/client/gui/Font$PreparedTextBuilder.glyphs:Ljava/util/List;
       115: invokeinterface #210,  1          // InterfaceMethod java/util/List.iterator:()Ljava/util/Iterator;
       120: astore        11
       122: aload         11
       124: invokeinterface #216,  1          // InterfaceMethod java/util/Iterator.hasNext:()Z
       129: ifeq          156
       132: aload         11
       134: invokeinterface #220,  1          // InterfaceMethod java/util/Iterator.next:()Ljava/lang/Object;
       139: checkcast     #222                // class net/minecraft/client/gui/font/TextRenderable
       142: astore        12
       144: aload         10
       146: aload         12
       148: invokeinterface #226,  2          // InterfaceMethod net/minecraft/client/gui/Font$GlyphVisitor.acceptGlyph:(Lnet/minecraft/client/gui/font/TextRenderable;)V
       153: goto          122
       156: new           #13                 // class net/minecraft/client/gui/Font$PreparedTextBuilder
       159: dup
       160: aload_0
       161: fload_2
       162: fload_3
       163: iload         4
       165: iconst_0
       166: invokespecial #178                // Method net/minecraft/client/gui/Font$PreparedTextBuilder."<init>":(Lnet/minecraft/client/gui/Font;FFIZ)V
       169: astore        11
       171: aload_1
       172: aload         11
       174: invokeinterface #194,  2          // InterfaceMethod net/minecraft/util/FormattedCharSequence.accept:(Lnet/minecraft/util/FormattedCharSink;)Z
       179: pop
       180: aload         11
       182: aload         7
       184: aload         6
       186: getstatic     #229                // Field net/minecraft/client/gui/Font$DisplayMode.POLYGON_OFFSET:Lnet/minecraft/client/gui/Font$DisplayMode;
       189: iload         8
       191: invokestatic  #148                // InterfaceMethod net/minecraft/client/gui/Font$GlyphVisitor.forMultiBufferSource:(Lnet/minecraft/client/renderer/MultiBufferSource;Lorg/joml/Matrix4f;Lnet/minecraft/client/gui/Font$DisplayMode;I)Lnet/minecraft/client/gui/Font$GlyphVisitor;
       194: invokevirtual #230                // Method net/minecraft/client/gui/Font$PreparedTextBuilder.visit:(Lnet/minecraft/client/gui/Font$GlyphVisitor;)V
       197: return

  net.minecraft.client.gui.font.glyphs.BakedGlyph getGlyph(int, net.minecraft.network.chat.Style);
    Code:
         0: aload_0
         1: aload_2
         2: invokevirtual #252                // Method net/minecraft/network/chat/Style.getFont:()Lnet/minecraft/network/chat/FontDescription;
         5: invokevirtual #254                // Method getGlyphSource:(Lnet/minecraft/network/chat/FontDescription;)Lnet/minecraft/client/gui/GlyphSource;
         8: astore_3
         9: aload_3
        10: iload_1
        11: invokeinterface #259,  2          // InterfaceMethod net/minecraft/client/gui/GlyphSource.getGlyph:(I)Lnet/minecraft/client/gui/font/glyphs/BakedGlyph;
        16: astore        4
        18: aload_2
        19: invokevirtual #262                // Method net/minecraft/network/chat/Style.isObfuscated:()Z
        22: ifeq          63
        25: iload_1
        26: bipush        32
        28: if_icmpeq     63
        31: aload         4
        33: invokeinterface #268,  1          // InterfaceMethod net/minecraft/client/gui/font/glyphs/BakedGlyph.info:()Lcom/mojang/blaze3d/font/GlyphInfo;
        38: iconst_0
        39: invokeinterface #274,  2          // InterfaceMethod com/mojang/blaze3d/font/GlyphInfo.getAdvance:(Z)F
        44: invokestatic  #280                // Method net/minecraft/util/Mth.ceil:(F)I
        47: istore        5
        49: aload_3
        50: aload_0
        51: getfield      #66                 // Field random:Lnet/minecraft/util/RandomSource;
        54: iload         5
        56: invokeinterface #284,  3          // InterfaceMethod net/minecraft/client/gui/GlyphSource.getRandomGlyph:(Lnet/minecraft/util/RandomSource;I)Lnet/minecraft/client/gui/font/glyphs/BakedGlyph;
        61: astore        4
        63: aload         4
        65: areturn

  public net.minecraft.client.gui.Font$PreparedText prepareText(java.lang.String, float, float, int, boolean, int);
    Code:
         0: aload_0
         1: invokevirtual #292                // Method isBidirectional:()Z
         4: ifeq          13
         7: aload_0
         8: aload_1
         9: invokevirtual #294                // Method bidirectionalShaping:(Ljava/lang/String;)Ljava/lang/String;
        12: astore_1
        13: new           #13                 // class net/minecraft/client/gui/Font$PreparedTextBuilder
        16: dup
        17: aload_0
        18: fload_2
        19: fload_3
        20: iload         4
        22: iload         6
        24: iload         5
        26: invokespecial #297                // Method net/minecraft/client/gui/Font$PreparedTextBuilder."<init>":(Lnet/minecraft/client/gui/Font;FFIIZ)V
        29: astore        7
        31: aload_1
        32: getstatic     #300                // Field net/minecraft/network/chat/Style.EMPTY:Lnet/minecraft/network/chat/Style;
        35: aload         7
        37: invokestatic  #306                // Method net/minecraft/util/StringDecomposer.iterateFormatted:(Ljava/lang/String;Lnet/minecraft/network/chat/Style;Lnet/minecraft/util/FormattedCharSink;)Z
        40: pop
        41: aload         7
        43: areturn

  public net.minecraft.client.gui.Font$PreparedText prepareText(net.minecraft.util.FormattedCharSequence, float, float, int, boolean, int);
    Code:
         0: new           #13                 // class net/minecraft/client/gui/Font$PreparedTextBuilder
         3: dup
         4: aload_0
         5: fload_2
         6: fload_3
         7: iload         4
         9: iload         6
        11: iload         5
        13: invokespecial #297                // Method net/minecraft/client/gui/Font$PreparedTextBuilder."<init>":(Lnet/minecraft/client/gui/Font;FFIIZ)V
        16: astore        7
        18: aload_1
        19: aload         7
        21: invokeinterface #194,  2          // InterfaceMethod net/minecraft/util/FormattedCharSequence.accept:(Lnet/minecraft/util/FormattedCharSink;)Z
        26: pop
        27: aload         7
        29: areturn

  public int width(java.lang.String);
    Code:
         0: aload_0
         1: getfield      #90                 // Field splitter:Lnet/minecraft/client/StringSplitter;
         4: aload_1
         5: invokevirtual #312                // Method net/minecraft/client/StringSplitter.stringWidth:(Ljava/lang/String;)F
         8: invokestatic  #280                // Method net/minecraft/util/Mth.ceil:(F)I
        11: ireturn

  public int width(net.minecraft.network.chat.FormattedText);
    Code:
         0: aload_0
         1: getfield      #90                 // Field splitter:Lnet/minecraft/client/StringSplitter;
         4: aload_1
         5: invokevirtual #317                // Method net/minecraft/client/StringSplitter.stringWidth:(Lnet/minecraft/network/chat/FormattedText;)F
         8: invokestatic  #280                // Method net/minecraft/util/Mth.ceil:(F)I
        11: ireturn

  public int width(net.minecraft.util.FormattedCharSequence);
    Code:
         0: aload_0
         1: getfield      #90                 // Field splitter:Lnet/minecraft/client/StringSplitter;
         4: aload_1
         5: invokevirtual #322                // Method net/minecraft/client/StringSplitter.stringWidth:(Lnet/minecraft/util/FormattedCharSequence;)F
         8: invokestatic  #280                // Method net/minecraft/util/Mth.ceil:(F)I
        11: ireturn

  public java.lang.String plainSubstrByWidth(java.lang.String, int, boolean);
    Code:
         0: iload_3
         1: ifeq          19
         4: aload_0
         5: getfield      #90                 // Field splitter:Lnet/minecraft/client/StringSplitter;
         8: aload_1
         9: iload_2
        10: getstatic     #300                // Field net/minecraft/network/chat/Style.EMPTY:Lnet/minecraft/network/chat/Style;
        13: invokevirtual #328                // Method net/minecraft/client/StringSplitter.plainTailByWidth:(Ljava/lang/String;ILnet/minecraft/network/chat/Style;)Ljava/lang/String;
        16: goto          31
        19: aload_0
        20: getfield      #90                 // Field splitter:Lnet/minecraft/client/StringSplitter;
        23: aload_1
        24: iload_2
        25: getstatic     #300                // Field net/minecraft/network/chat/Style.EMPTY:Lnet/minecraft/network/chat/Style;
        28: invokevirtual #331                // Method net/minecraft/client/StringSplitter.plainHeadByWidth:(Ljava/lang/String;ILnet/minecraft/network/chat/Style;)Ljava/lang/String;
        31: areturn

  public java.lang.String plainSubstrByWidth(java.lang.String, int);
    Code:
         0: aload_0
         1: getfield      #90                 // Field splitter:Lnet/minecraft/client/StringSplitter;
         4: aload_1
         5: iload_2
         6: getstatic     #300                // Field net/minecraft/network/chat/Style.EMPTY:Lnet/minecraft/network/chat/Style;
         9: invokevirtual #331                // Method net/minecraft/client/StringSplitter.plainHeadByWidth:(Ljava/lang/String;ILnet/minecraft/network/chat/Style;)Ljava/lang/String;
        12: areturn

  public net.minecraft.network.chat.FormattedText substrByWidth(net.minecraft.network.chat.FormattedText, int);
    Code:
         0: aload_0
         1: getfield      #90                 // Field splitter:Lnet/minecraft/client/StringSplitter;
         4: aload_1
         5: iload_2
         6: getstatic     #300                // Field net/minecraft/network/chat/Style.EMPTY:Lnet/minecraft/network/chat/Style;
         9: invokevirtual #338                // Method net/minecraft/client/StringSplitter.headByWidth:(Lnet/minecraft/network/chat/FormattedText;ILnet/minecraft/network/chat/Style;)Lnet/minecraft/network/chat/FormattedText;
        12: areturn

  public int wordWrapHeight(java.lang.String, int);
    Code:
         0: bipush        9
         2: aload_0
         3: getfield      #90                 // Field splitter:Lnet/minecraft/client/StringSplitter;
         6: aload_1
         7: iload_2
         8: getstatic     #300                // Field net/minecraft/network/chat/Style.EMPTY:Lnet/minecraft/network/chat/Style;
        11: invokevirtual #344                // Method net/minecraft/client/StringSplitter.splitLines:(Ljava/lang/String;ILnet/minecraft/network/chat/Style;)Ljava/util/List;
        14: invokeinterface #348,  1          // InterfaceMethod java/util/List.size:()I
        19: imul
        20: ireturn

  public int wordWrapHeight(net.minecraft.network.chat.FormattedText, int);
    Code:
         0: bipush        9
         2: aload_0
         3: getfield      #90                 // Field splitter:Lnet/minecraft/client/StringSplitter;
         6: aload_1
         7: iload_2
         8: getstatic     #300                // Field net/minecraft/network/chat/Style.EMPTY:Lnet/minecraft/network/chat/Style;
        11: invokevirtual #352                // Method net/minecraft/client/StringSplitter.splitLines:(Lnet/minecraft/network/chat/FormattedText;ILnet/minecraft/network/chat/Style;)Ljava/util/List;
        14: invokeinterface #348,  1          // InterfaceMethod java/util/List.size:()I
        19: imul
        20: ireturn

  public java.util.List<net.minecraft.util.FormattedCharSequence> split(net.minecraft.network.chat.FormattedText, int);
    Code:
         0: invokestatic  #361                // Method net/minecraft/locale/Language.getInstance:()Lnet/minecraft/locale/Language;
         3: aload_0
         4: getfield      #90                 // Field splitter:Lnet/minecraft/client/StringSplitter;
         7: aload_1
         8: iload_2
         9: getstatic     #300                // Field net/minecraft/network/chat/Style.EMPTY:Lnet/minecraft/network/chat/Style;
        12: invokevirtual #352                // Method net/minecraft/client/StringSplitter.splitLines:(Lnet/minecraft/network/chat/FormattedText;ILnet/minecraft/network/chat/Style;)Ljava/util/List;
        15: invokevirtual #365                // Method net/minecraft/locale/Language.getVisualOrder:(Ljava/util/List;)Ljava/util/List;
        18: areturn

  public java.util.List<net.minecraft.network.chat.FormattedText> splitIgnoringLanguage(net.minecraft.network.chat.FormattedText, int);
    Code:
         0: aload_0
         1: getfield      #90                 // Field splitter:Lnet/minecraft/client/StringSplitter;
         4: aload_1
         5: iload_2
         6: getstatic     #300                // Field net/minecraft/network/chat/Style.EMPTY:Lnet/minecraft/network/chat/Style;
         9: invokevirtual #352                // Method net/minecraft/client/StringSplitter.splitLines:(Lnet/minecraft/network/chat/FormattedText;ILnet/minecraft/network/chat/Style;)Ljava/util/List;
        12: areturn

  public boolean isBidirectional();
    Code:
         0: invokestatic  #361                // Method net/minecraft/locale/Language.getInstance:()Lnet/minecraft/locale/Language;
         3: invokevirtual #370                // Method net/minecraft/locale/Language.isDefaultRightToLeft:()Z
         6: ireturn

  public net.minecraft.client.StringSplitter getSplitter();
    Code:
         0: aload_0
         1: getfield      #90                 // Field splitter:Lnet/minecraft/client/StringSplitter;
         4: areturn

  private boolean method_37297(net.minecraft.client.gui.Font$PreparedTextBuilder, float[], int, float, int, int, int, net.minecraft.network.chat.Style, int);
    Code:
         0: aload         8
         2: invokevirtual #375                // Method net/minecraft/network/chat/Style.isBold:()Z
         5: istore        10
         7: aload_0
         8: iload         9
        10: aload         8
        12: invokevirtual #377                // Method getGlyph:(ILnet/minecraft/network/chat/Style;)Lnet/minecraft/client/gui/font/glyphs/BakedGlyph;
        15: astore        11
        17: aload_1
        18: aload_2
        19: iconst_0
        20: faload
        21: iload_3
        22: i2f
        23: aload         11
        25: invokeinterface #268,  1          // InterfaceMethod net/minecraft/client/gui/font/glyphs/BakedGlyph.info:()Lcom/mojang/blaze3d/font/GlyphInfo;
        30: invokeinterface #381,  1          // InterfaceMethod com/mojang/blaze3d/font/GlyphInfo.getShadowOffset:()F
        35: fmul
        36: fadd
        37: putfield      #384                // Field net/minecraft/client/gui/Font$PreparedTextBuilder.x:F
        40: aload_1
        41: fload         4
        43: iload         5
        45: i2f
        46: aload         11
        48: invokeinterface #268,  1          // InterfaceMethod net/minecraft/client/gui/font/glyphs/BakedGlyph.info:()Lcom/mojang/blaze3d/font/GlyphInfo;
        53: invokeinterface #381,  1          // InterfaceMethod com/mojang/blaze3d/font/GlyphInfo.getShadowOffset:()F
        58: fmul
        59: fadd
        60: putfield      #387                // Field net/minecraft/client/gui/Font$PreparedTextBuilder.y:F
        63: aload_2
        64: iconst_0
        65: dup2
        66: faload
        67: aload         11
        69: invokeinterface #268,  1          // InterfaceMethod net/minecraft/client/gui/font/glyphs/BakedGlyph.info:()Lcom/mojang/blaze3d/font/GlyphInfo;
        74: iload         10
        76: invokeinterface #274,  2          // InterfaceMethod com/mojang/blaze3d/font/GlyphInfo.getAdvance:(Z)F
        81: fadd
        82: fastore
        83: aload_1
        84: iload         7
        86: aload         8
        88: iload         6
        90: invokevirtual #391                // Method net/minecraft/network/chat/Style.withColor:(I)Lnet/minecraft/network/chat/Style;
        93: aload         11
        95: invokevirtual #394                // Method net/minecraft/client/gui/Font$PreparedTextBuilder.accept:(ILnet/minecraft/network/chat/Style;Lnet/minecraft/client/gui/font/glyphs/BakedGlyph;)Z
        98: ireturn

  private float method_27516(int, net.minecraft.network.chat.Style);
    Code:
         0: aload_0
         1: aload_2
         2: invokevirtual #252                // Method net/minecraft/network/chat/Style.getFont:()Lnet/minecraft/network/chat/FontDescription;
         5: invokevirtual #254                // Method getGlyphSource:(Lnet/minecraft/network/chat/FontDescription;)Lnet/minecraft/client/gui/GlyphSource;
         8: iload_1
         9: invokeinterface #259,  2          // InterfaceMethod net/minecraft/client/gui/GlyphSource.getGlyph:(I)Lnet/minecraft/client/gui/font/glyphs/BakedGlyph;
        14: invokeinterface #268,  1          // InterfaceMethod net/minecraft/client/gui/font/glyphs/BakedGlyph.info:()Lcom/mojang/blaze3d/font/GlyphInfo;
        19: aload_2
        20: invokevirtual #375                // Method net/minecraft/network/chat/Style.isBold:()Z
        23: invokeinterface #274,  2          // InterfaceMethod com/mojang/blaze3d/font/GlyphInfo.getAdvance:(Z)F
        28: freturn
}
